{
	"W_181792": {
		"P_674774": {
			"work_title": "What Have We Become?",
			"work_artist": "Mark Heimermann",
			"perf_title": "What Have We Become?",
			"perf_artist": "dc Talk",
			"release_year": "1995",
			"work_id": "W_181792",
			"perf_id": "P_674774",
			"yt_link": "http://www.youtube.com/embed/TlbAwVMZq0Q",
			"instrumental": "No"
		},
		"P_674775": {
			"work_title": "What Have We Become?",
			"work_artist": "Mark Heimermann",
			"perf_title": "What Have We Become?",
			"perf_artist": "Liquid",
			"release_year": "2006",
			"work_id": "W_181792",
			"perf_id": "P_674775",
			"yt_link": "http://www.youtube.com/embed/4NvcMSH2-o0",
			"instrumental": "No"
		}
	},
	"W_181793": {
		"P_674777": {
			"work_title": "Mind's Eye",
			"work_artist": "Mark Heimermann",
			"perf_title": "Mind's Eye",
			"perf_artist": "dc Talk",
			"release_year": "1995",
			"work_id": "W_181793",
			"perf_id": "P_674777",
			"yt_link": "http://www.youtube.com/embed/qBVdrQt7xQo",
			"instrumental": "No"
		},
		"P_674778": {
			"work_title": "Mind's Eye",
			"work_artist": "Mark Heimermann",
			"perf_title": "Mind's Eye",
			"perf_artist": "Family Force 5",
			"release_year": "2006",
			"work_id": "W_181793",
			"perf_id": "P_674778",
			"yt_link": "http://www.youtube.com/embed/bSEWlpGGNo4",
			"instrumental": "No"
		}
	},
	"W_181794": {
		"P_674787": {
			"work_title": "Free",
			"work_artist": "Michael Sweet",
			"perf_title": "Free",
			"perf_artist": "Stryper",
			"release_year": "1986",
			"work_id": "W_181794",
			"perf_id": "P_674787",
			"yt_link": "http://www.youtube.com/embed/KDLF5Or1HpU",
			"instrumental": "No"
		},
		"P_674788": {
			"work_title": "Free",
			"work_artist": "Michael Sweet",
			"perf_title": "Free",
			"perf_artist": "Marriage is Madness",
			"release_year": "1996",
			"work_id": "W_181794",
			"perf_id": "P_674788",
			"yt_link": "http://www.youtube.com/embed/dun-2xLXSeI",
			"instrumental": "No"
		}
	},
	"W_181797": {
		"P_674810": {
			"work_title": "Cosmic Cowboy",
			"work_artist": "Barry McGuire",
			"perf_title": "Cosmic Cowboy",
			"perf_artist": "Barry McGuire",
			"release_year": "1978",
			"work_id": "W_181797",
			"perf_id": "P_674810",
			"yt_link": "http://www.youtube.com/embed/XHgLSq_srFI",
			"instrumental": "No"
		},
		"P_674813": {
			"work_title": "Cosmic Cowboy",
			"work_artist": "Barry McGuire",
			"perf_title": "Cosmic Cowboy",
			"perf_artist": "One Bad Pig",
			"release_year": "1998",
			"work_id": "W_181797",
			"perf_id": "P_674813",
			"yt_link": "http://www.youtube.com/embed/m4B5INtAfs8",
			"instrumental": "No"
		}
	},
	"W_181806": {
		"P_674889": {
			"work_title": "If I Ever Love Again",
			"work_artist": "Dick Reynolds",
			"perf_title": "If I Ever Love Again",
			"perf_artist": "Jo Stafford with Paul Weston and His Orchestra",
			"release_year": "1949",
			"work_id": "W_181806",
			"perf_id": "P_674889",
			"yt_link": "http://www.youtube.com/embed/HU0kEGmiB9M",
			"instrumental": "No"
		}
	},
	"W_181807": {},
	"W_181811": {
		"P_674989": {
			"work_title": "My Blues Have Gone",
			"work_artist": "Kim Beacon",
			"perf_title": "My Blues Have Gone",
			"perf_artist": "Kim Beacon",
			"release_year": "1979",
			"work_id": "W_181811",
			"perf_id": "P_674989",
			"yt_link": "http://www.youtube.com/embed/h9K7p7ZQzs0",
			"instrumental": "No"
		}
	},
	"W_181815": {
		"P_675020": {
			"work_title": "If I Give You My Heart",
			"work_artist": "Sunny Hilden",
			"perf_title": "If I Give You My Heart",
			"perf_artist": "The Temptations",
			"release_year": "1998",
			"work_id": "W_181815",
			"perf_id": "P_675020",
			"yt_link": "http://www.youtube.com/embed/Uz41kdXZWWQ",
			"instrumental": "No"
		},
		"P_675018": {
			"work_title": "If I Give You My Heart",
			"work_artist": "Sunny Hilden",
			"perf_title": "If I Give You My Heart",
			"perf_artist": "Robertson Brothers",
			"release_year": "2002",
			"work_id": "W_181815",
			"perf_id": "P_675018",
			"yt_link": "http://www.youtube.com/embed/v8LNTsAS_ag",
			"instrumental": "No"
		}
	},
	"W_181816": {
		"P_675047": {
			"work_title": "When God-Fearin' Women Get the Blues",
			"work_artist": "Leslie Satcher",
			"perf_title": "When God-Fearin' Women Get the Blues",
			"perf_artist": "Martina McBride",
			"release_year": "2001",
			"work_id": "W_181816",
			"perf_id": "P_675047",
			"yt_link": "http://www.youtube.com/embed/Aq1CuhcDj8Y",
			"instrumental": "No"
		},
		"P_675046": {
			"work_title": "When God-Fearin' Women Get the Blues",
			"work_artist": "Leslie Satcher",
			"perf_title": "When God-Fearin' Women Get the Blues",
			"perf_artist": "Holly Tucker",
			"release_year": "2013",
			"work_id": "W_181816",
			"perf_id": "P_675046",
			"yt_link": "http://www.youtube.com/embed/oOmmIYMVN-A",
			"instrumental": "No"
		}
	},
	"W_181824": {},
	"W_181941": {},
	"W_181946": {
		"P_675939": {
			"work_title": "Country Music in My Soul",
			"work_artist": "Bobby Bond",
			"perf_title": "Country Music in My Soul",
			"perf_artist": "George Hamilton IV",
			"release_year": "1972",
			"work_id": "W_181946",
			"perf_id": "P_675939",
			"yt_link": "http://www.youtube.com/embed/B4Z0QbufKq4",
			"instrumental": "No"
		},
		"P_675940": {
			"work_title": "Country Music in My Soul",
			"work_artist": "Bobby Bond",
			"perf_title": "Country Music in My Soul",
			"perf_artist": "George Hamilton IV, Ji\u0159\u00ed Brabec & Country Beat",
			"release_year": "1984",
			"work_id": "W_181946",
			"perf_id": "P_675940",
			"yt_link": "http://www.youtube.com/embed/KIVk1cskVFY",
			"instrumental": "No"
		}
	},
	"W_181949": {},
	"W_181962": {
		"P_676043": {
			"work_title": "Dear Christine",
			"work_artist": "John Woloschuk",
			"perf_title": "Dear Christine",
			"perf_artist": "Klaatu",
			"release_year": "1978",
			"work_id": "W_181962",
			"perf_id": "P_676043",
			"yt_link": "http://www.youtube.com/embed/YNdql7ShBOg",
			"instrumental": "No"
		}
	},
	"W_181963": {
		"P_676059": {
			"work_title": "Thank You",
			"work_artist": "Stan Freberg",
			"perf_title": "Wun'erful, Wun'erful! (Side Uh-one)",
			"perf_artist": "Stan Freberg with Billy May's Music featuring Chuck Schrouder and The Lemon Sisters",
			"release_year": "1957",
			"work_id": "W_181963",
			"perf_id": "P_676059",
			"yt_link": "http://www.youtube.com/embed/YWaO5v5GJSE",
			"instrumental": "No"
		}
	},
	"W_181969": {
		"P_676281": {
			"work_title": "This Train Don't Stop There Anymore",
			"work_artist": "Elton John",
			"perf_title": "This Train Don't Stop There Anymore",
			"perf_artist": "Elton John",
			"release_year": "2001",
			"work_id": "W_181969",
			"perf_id": "P_676281",
			"yt_link": "http://www.youtube.com/embed/PO0x8pW-ATY",
			"instrumental": "No"
		},
		"P_676271": {
			"work_title": "This Train Don't Stop There Anymore",
			"work_artist": "Elton John",
			"perf_title": "This Train Don't Stop There Anymore",
			"perf_artist": "Rosanne Cash & Emmylou Harris",
			"release_year": "2018",
			"work_id": "W_181969",
			"perf_id": "P_676271",
			"yt_link": "http://www.youtube.com/embed/Jh8O-4F4vko",
			"instrumental": "No"
		}
	},
	"W_181970": {
		"P_676273": {
			"work_title": "Please",
			"work_artist": "Elton John",
			"perf_title": "Please",
			"perf_artist": "Elton John",
			"release_year": "1995",
			"work_id": "W_181970",
			"perf_id": "P_676273",
			"yt_link": "http://www.youtube.com/embed/xEemkE1e8n8",
			"instrumental": "No"
		},
		"P_676276": {
			"work_title": "Please",
			"work_artist": "Elton John",
			"perf_title": "Please",
			"perf_artist": "Rhonda Vincent & Dolly Parton",
			"release_year": "2018",
			"work_id": "W_181970",
			"perf_id": "P_676276",
			"yt_link": "http://www.youtube.com/embed/MFI_AMUeZ7o",
			"instrumental": "No"
		}
	},
	"W_181971": {
		"P_676274": {
			"work_title": "Roy Rogers",
			"work_artist": "Elton John",
			"perf_title": "Roy Rogers",
			"perf_artist": "Elton John",
			"release_year": "1973",
			"work_id": "W_181971",
			"perf_id": "P_676274",
			"yt_link": "http://www.youtube.com/embed/m2yRASZqKeM",
			"instrumental": "No"
		},
		"P_676275": {
			"work_title": "Roy Rogers",
			"work_artist": "Elton John",
			"perf_title": "Roy Rogers",
			"perf_artist": "Kacey Musgraves",
			"release_year": "2018",
			"work_id": "W_181971",
			"perf_id": "P_676275",
			"yt_link": "http://www.youtube.com/embed/8CPGTI_eBK4",
			"instrumental": "No"
		}
	},
	"W_181972": {
		"P_676278": {
			"work_title": "My Father's Gun",
			"work_artist": "Elton John",
			"perf_title": "My Father's Gun",
			"perf_artist": "Elton John",
			"release_year": "1970",
			"work_id": "W_181972",
			"perf_id": "P_676278",
			"yt_link": "http://www.youtube.com/embed/R_p0lbEuKzk",
			"instrumental": "No"
		},
		"P_676277": {
			"work_title": "My Father's Gun",
			"work_artist": "Elton John",
			"perf_title": "My Father's Gun",
			"perf_artist": "Miranda Lambert",
			"release_year": "2018",
			"work_id": "W_181972",
			"perf_id": "P_676277",
			"yt_link": "http://www.youtube.com/embed/0ZTdBC1tfDw",
			"instrumental": "No"
		}
	},
	"W_181988": {},
	"W_182010": {},
	"W_182012": {
		"P_676382": {
			"work_title": "Deborah",
			"work_artist": "Vangelis",
			"perf_title": "Deborah",
			"perf_artist": "Jon and Vangelis",
			"release_year": "1983",
			"work_id": "W_182012",
			"perf_id": "P_676382",
			"yt_link": "http://www.youtube.com/embed/ko4626ABlU4",
			"instrumental": "No"
		}
	},
	"W_182017": {
		"P_676389": {
			"work_title": "One More Arrow",
			"work_artist": "Elton John",
			"perf_title": "One More Arrow",
			"perf_artist": "Elton John",
			"release_year": "1983",
			"work_id": "W_182017",
			"perf_id": "P_676389",
			"yt_link": "http://www.youtube.com/embed/JxO8CAKumYw",
			"instrumental": "No"
		}
	},
	"W_182028": {
		"P_676558": {
			"work_title": "Allelujah",
			"work_artist": "Mark E. Nevin",
			"perf_title": "Allelujah",
			"perf_artist": "Fairground Attraction",
			"release_year": "1988",
			"work_id": "W_182028",
			"perf_id": "P_676558",
			"yt_link": "http://www.youtube.com/embed/iQrzE5Peouw",
			"instrumental": "No"
		},
		"P_676559": {
			"work_title": "Allelujah",
			"work_artist": "Mark E. Nevin",
			"perf_title": "Allelujah",
			"perf_artist": "Ann Sally",
			"release_year": "2003",
			"work_id": "W_182028",
			"perf_id": "P_676559",
			"yt_link": "http://www.youtube.com/embed/qdsTSiMd-1w",
			"instrumental": "No"
		}
	},
	"W_182030": {
		"P_676664": {
			"work_title": "Wishing I Was Lucky",
			"work_artist": "Tommy Cunningham",
			"perf_title": "Wishing I Was Lucky",
			"perf_artist": "Wet Wet Wet",
			"release_year": "1987",
			"work_id": "W_182030",
			"perf_id": "P_676664",
			"yt_link": "http://www.youtube.com/embed/BKKZ9y_BpXU",
			"instrumental": "No"
		}
	},
	"W_182031": {
		"P_676680": {
			"work_title": "L\u00e1sko posmutn\u011bl\u00e1",
			"work_artist": "Bohuslav Ondr\u00e1\u010dek",
			"perf_title": "L\u00e1sko posmutn\u011bl\u00e1",
			"perf_artist": "Jitka Zelenkov\u00e1",
			"release_year": "1982",
			"work_id": "W_182031",
			"perf_id": "P_676680",
			"yt_link": "http://www.youtube.com/embed/EQ8Rk6MmiUM",
			"instrumental": "No"
		}
	},
	"W_182034": {},
	"W_182036": {
		"P_676690": {
			"work_title": "A ty to v\u00ed\u0161",
			"work_artist": "Karel Svoboda",
			"perf_title": "A ty to v\u00ed\u0161",
			"perf_artist": "Jitka Zelenkov\u00e1",
			"release_year": "1982",
			"work_id": "W_182036",
			"perf_id": "P_676690",
			"yt_link": "http://www.youtube.com/embed/1LZCnzfAR5A",
			"instrumental": "No"
		}
	},
	"W_182047": {
		"P_678200": {
			"work_title": "Catchphrase",
			"work_artist": "Ed Welch",
			"perf_title": "Catchphrase",
			"perf_artist": "[Unknown Studio Artist(s)]",
			"release_year": "",
			"work_id": "W_182047",
			"perf_id": "P_678200",
			"yt_link": "http://www.youtube.com/embed/Uh1xhdeVE_c",
			"instrumental": "Yes"
		}
	},
	"W_182049": {
		"P_676995": {
			"work_title": "Fancy Pants",
			"work_artist": "Acker Bilk",
			"perf_title": "Fancy Pants",
			"perf_artist": "Mr. Acker Bilk and His Paramount Jazz Band",
			"release_year": "1960",
			"work_id": "W_182049",
			"perf_id": "P_676995",
			"yt_link": "http://www.youtube.com/embed/5tfLYJii1Bk",
			"instrumental": "Yes"
		}
	},
	"W_182066": {},
	"W_182075": {
		"P_677038": {
			"work_title": "One More Rhythm",
			"work_artist": "Rod Temperton",
			"perf_title": "One More Rhythm",
			"perf_artist": "James Ingram",
			"release_year": "1983",
			"work_id": "W_182075",
			"perf_id": "P_677038",
			"yt_link": "http://www.youtube.com/embed/W9vBPDhERts",
			"instrumental": "No"
		}
	},
	"W_182084": {},
	"W_182085": {},
	"W_182087": {},
	"W_182088": {},
	"W_182089": {
		"P_677070": {
			"work_title": "Dat",
			"work_artist": "Michael Simmons",
			"perf_title": "Dat",
			"perf_artist": "sparkle*jets u.k.",
			"release_year": "1998",
			"work_id": "W_182089",
			"perf_id": "P_677070",
			"yt_link": "http://www.youtube.com/embed/vErnLFnaM-I",
			"instrumental": "No"
		}
	},
	"W_182091": {},
	"W_182092": {},
	"W_182093": {},
	"W_182095": {},
	"W_182098": {},
	"W_182103": {
		"P_677100": {
			"work_title": "New York, New York",
			"work_artist": "Gerard Kenny",
			"perf_title": "New York, New York",
			"perf_artist": "Gerard Kenny",
			"release_year": "1979",
			"work_id": "W_182103",
			"perf_id": "P_677100",
			"yt_link": "http://www.youtube.com/embed/pUyDHwXvJ8A",
			"instrumental": "No"
		},
		"P_677105": {
			"work_title": "New York, New York",
			"work_artist": "Gerard Kenny",
			"perf_title": "New York Medley [New York, New York]",
			"perf_artist": "Shirley Bassey",
			"release_year": "1982",
			"work_id": "W_182103",
			"perf_id": "P_677105",
			"yt_link": "http://www.youtube.com/embed/SvxTh_oxH64",
			"instrumental": "No"
		}
	},
	"W_182107": {
		"P_677123": {
			"work_title": "Donna Twist",
			"work_artist": "Riz Ortolani",
			"perf_title": "Donna Twist",
			"perf_artist": "Riz Ortolani",
			"release_year": "1963",
			"work_id": "W_182107",
			"perf_id": "P_677123",
			"yt_link": "http://www.youtube.com/embed/244eFrqE5uw",
			"instrumental": "Yes"
		}
	},
	"W_182108": {},
	"W_182118": {
		"P_677163": {
			"work_title": "Don't You Know That?",
			"work_artist": "Luther Vandross",
			"perf_title": "Don't You Know That?",
			"perf_artist": "Luther Vandross",
			"release_year": "1981",
			"work_id": "W_182118",
			"perf_id": "P_677163",
			"yt_link": "http://www.youtube.com/embed/Hgh7w_cfSOk",
			"instrumental": "No"
		}
	},
	"W_182215": {},
	"W_182216": {
		"P_678060": {
			"work_title": "Dempsey and Makepeace",
			"work_artist": "Alan Parker",
			"perf_title": "Dempsey & Makepeace",
			"perf_artist": "The South Bank Orchestra",
			"release_year": "1985",
			"work_id": "W_182216",
			"perf_id": "P_678060",
			"yt_link": "http://www.youtube.com/embed/a10c6Xj59JM",
			"instrumental": "Yes"
		}
	},
	"W_182217": {
		"P_678066": {
			"work_title": "Peak Performance [Treasure Hunt]",
			"work_artist": "Zack Laurence",
			"perf_title": "Peak Performance [Treasure Hunt]",
			"perf_artist": "Zack Laurence",
			"release_year": "1982",
			"work_id": "W_182217",
			"perf_id": "P_678066",
			"yt_link": "http://www.youtube.com/embed/xEV5bVDb9m8",
			"instrumental": "Yes"
		},
		"P_678067": {
			"work_title": "Peak Performance [Treasure Hunt]",
			"work_artist": "Zack Laurence",
			"perf_title": "Treasure Hunt",
			"perf_artist": "Dream Themes",
			"release_year": "2017",
			"work_id": "W_182217",
			"perf_id": "P_678067",
			"yt_link": "http://www.youtube.com/embed/fdESjm-UKXs",
			"instrumental": "Yes"
		}
	},
	"W_182224": {
		"P_678157": {
			"work_title": "I Still Love You",
			"work_artist": "Raphael Brown",
			"perf_title": "I Still Love You",
			"perf_artist": "Next",
			"release_year": "1997",
			"work_id": "W_182224",
			"perf_id": "P_678157",
			"yt_link": "http://www.youtube.com/embed/PqiIc4QXofI",
			"instrumental": "No"
		}
	},
	"W_182225": {
		"P_678214": {
			"work_title": "Take It Easy",
			"work_artist": "Xavier Cugat",
			"perf_title": "Take It Easy",
			"perf_artist": "Xavier Cugat and His Orchestra",
			"release_year": "1955",
			"work_id": "W_182225",
			"perf_id": "P_678214",
			"yt_link": "http://www.youtube.com/embed/3L7sUmEwuaM",
			"instrumental": "No"
		},
		"P_678216": {
			"work_title": "Take It Easy",
			"work_artist": "Xavier Cugat",
			"perf_title": "Take It Easy",
			"perf_artist": "Abbe Lane with Tito Puente and His Orchestra",
			"release_year": "1957",
			"work_id": "W_182225",
			"perf_id": "P_678216",
			"yt_link": "http://www.youtube.com/embed/LaMYoaDqf20",
			"instrumental": "No"
		}
	},
	"W_182228": {},
	"W_182233": {
		"P_678248": {
			"work_title": "Jacob and Two Women",
			"work_artist": "Rich Mullins",
			"perf_title": "Jacob and 2 Women",
			"perf_artist": "Rich Mullins",
			"release_year": "1991",
			"work_id": "W_182233",
			"perf_id": "P_678248",
			"yt_link": "http://www.youtube.com/embed/RFkYUuCzmZY",
			"instrumental": "No"
		},
		"P_678249": {
			"work_title": "Jacob and Two Women",
			"work_artist": "Rich Mullins",
			"perf_title": "Jacob and 2 Women",
			"perf_artist": "Carolyn Arends",
			"release_year": "1998",
			"work_id": "W_182233",
			"perf_id": "P_678249",
			"yt_link": "http://www.youtube.com/embed/SQoHwxwOf_k",
			"instrumental": "No"
		}
	},
	"W_182236": {
		"P_678252": {
			"work_title": "Verge of a Miracle",
			"work_artist": "Rich Mullins",
			"perf_title": "Verge of a Miracle",
			"perf_artist": "Rich Mullins",
			"release_year": "1987",
			"work_id": "W_182236",
			"perf_id": "P_678252",
			"yt_link": "http://www.youtube.com/embed/2RF355U7gBg",
			"instrumental": "No"
		}
	},
	"W_181848": {
		"P_675220": {
			"work_title": "The Kiss",
			"work_artist": "Trevor Jones",
			"perf_title": "The Kiss",
			"perf_artist": "Trevor Jones - Randy Edelman",
			"release_year": "1992",
			"work_id": "W_181848",
			"perf_id": "P_675220",
			"yt_link": "http://www.youtube.com/embed/KG9Pb4a_xuM",
			"instrumental": "Yes"
		}
	},
	"W_181854": {
		"P_675251": {
			"work_title": "Portuguese Love Theme",
			"work_artist": "Craig Armstrong",
			"perf_title": "Portuguese Love Theme",
			"perf_artist": "Craig Armstrong",
			"release_year": "2003",
			"work_id": "W_181854",
			"perf_id": "P_675251",
			"yt_link": "http://www.youtube.com/embed/qRJ4iwGe22Y",
			"instrumental": "Yes"
		},
		"P_675252": {
			"work_title": "Portuguese Love Theme",
			"work_artist": "Craig Armstrong",
			"perf_title": "Portuguese Love Theme",
			"perf_artist": "Cairn String Quartet",
			"release_year": "2013",
			"work_id": "W_181854",
			"perf_id": "P_675252",
			"yt_link": "http://www.youtube.com/embed/7MR3T5aR_64",
			"instrumental": "Yes"
		}
	},
	"W_181860": {
		"P_675303": {
			"work_title": "The Secret Wedding",
			"work_artist": "James Horner",
			"perf_title": "The Secret Wedding",
			"perf_artist": "James Horner -  The London Symphony Orchestra",
			"release_year": "1995",
			"work_id": "W_181860",
			"perf_id": "P_675303",
			"yt_link": "http://www.youtube.com/embed/Ek6YqhZRttg",
			"instrumental": "Yes"
		},
		"P_675304": {
			"work_title": "The Secret Wedding",
			"work_artist": "James Horner",
			"perf_title": "For the Love of a Princess / The Secret Wedding",
			"perf_artist": "Cairn String Quartet",
			"release_year": "2013",
			"work_id": "W_181860",
			"perf_id": "P_675304",
			"yt_link": "http://www.youtube.com/embed/9h-fSk3GDyI",
			"instrumental": "Yes"
		}
	},
	"W_181862": {
		"P_675321": {
			"work_title": "Dive",
			"work_artist": "Steven Curtis Chapman",
			"perf_title": "Dive",
			"perf_artist": "Steven Curtis Chapman",
			"release_year": "1999",
			"work_id": "W_181862",
			"perf_id": "P_675321",
			"yt_link": "http://www.youtube.com/embed/hXqXIicm8uU",
			"instrumental": "No"
		},
		"P_675322": {
			"work_title": "Dive",
			"work_artist": "Steven Curtis Chapman",
			"perf_title": "Dive",
			"perf_artist": "Veggietales with Steven Curtis Chapman",
			"release_year": "2007",
			"work_id": "W_181862",
			"perf_id": "P_675322",
			"yt_link": "http://www.youtube.com/embed/_1UhM5yonBQ",
			"instrumental": "No"
		}
	},
	"W_181865": {
		"P_675376": {
			"work_title": "Blue Skies",
			"work_artist": "Grant Cunningham",
			"perf_title": "Blue Skies",
			"perf_artist": "Point of Grace",
			"release_year": "2001",
			"work_id": "W_181865",
			"perf_id": "P_675376",
			"yt_link": "http://www.youtube.com/embed/qRU9XYOZg2c",
			"instrumental": "No"
		}
	},
	"W_181866": {
		"P_675397": {
			"work_title": "Made to Love",
			"work_artist": "Cary Barlowe",
			"perf_title": "Made to Love",
			"perf_artist": "tobyMac",
			"release_year": "2006",
			"work_id": "W_181866",
			"perf_id": "P_675397",
			"yt_link": "http://www.youtube.com/embed/Qelx04Iu_3w",
			"instrumental": "No"
		}
	},
	"W_181867": {
		"P_675404": {
			"work_title": "Smellin' Coffee",
			"work_artist": "Chris Rice",
			"perf_title": "Smellin' Coffee",
			"perf_artist": "Chris Rice",
			"release_year": "1998",
			"work_id": "W_181867",
			"perf_id": "P_675404",
			"yt_link": "http://www.youtube.com/embed/ybRWDbnBLVY",
			"instrumental": "No"
		},
		"P_675405": {
			"work_title": "Smellin' Coffee",
			"work_artist": "Chris Rice",
			"perf_title": "Smellin' Coffee",
			"perf_artist": "Veggietales",
			"release_year": "2007",
			"work_id": "W_181867",
			"perf_id": "P_675405",
			"yt_link": "http://www.youtube.com/embed/JSL4qtBTDkU",
			"instrumental": "No"
		}
	},
	"W_181873": {},
	"W_181874": {
		"P_675496": {
			"work_title": "Summertime Dreamin'",
			"work_artist": "Barry Murray",
			"perf_title": "Summertime Dreaming",
			"perf_artist": "Gene Pitney",
			"release_year": "1972",
			"work_id": "W_181874",
			"perf_id": "P_675496",
			"yt_link": "http://www.youtube.com/embed/vv7trWkQiNI",
			"instrumental": "No"
		}
	},
	"W_181875": {
		"P_675498": {
			"work_title": "River",
			"work_artist": "Naughty Boy",
			"perf_title": "River",
			"perf_artist": "Emeli Sand\u00e9",
			"release_year": "2012",
			"work_id": "W_181875",
			"perf_id": "P_675498",
			"yt_link": "http://www.youtube.com/embed/rug36jGzlgU",
			"instrumental": "No"
		}
	},
	"W_181876": {},
	"W_181877": {
		"P_675503": {
			"work_title": "Real Nice Time",
			"work_artist": "Jamie Knight",
			"perf_title": "Real Nice Time",
			"perf_artist": "sparkle*jets u.k.",
			"release_year": "2001",
			"work_id": "W_181877",
			"perf_id": "P_675503",
			"yt_link": "http://www.youtube.com/embed/PA2FQ8-HwFM",
			"instrumental": "No"
		}
	},
	"W_181878": {
		"P_675505": {
			"work_title": "It's Gotta Happen",
			"work_artist": "Michael Simmons",
			"perf_title": "It's Gotta Happen",
			"perf_artist": "sparkle*jets u.k.",
			"release_year": "2001",
			"work_id": "W_181878",
			"perf_id": "P_675505",
			"yt_link": "http://www.youtube.com/embed/ky9dzwE1hwQ",
			"instrumental": "No"
		}
	},
	"W_181879": {
		"P_675522": {
			"work_title": "Place in This World",
			"work_artist": "Amy Grant",
			"perf_title": "Place in This World",
			"perf_artist": "Michael W. Smith",
			"release_year": "1990",
			"work_id": "W_181879",
			"perf_id": "P_675522",
			"yt_link": "http://www.youtube.com/embed/LpXMnY_t03M",
			"instrumental": "No"
		}
	},
	"W_181881": {
		"P_675548": {
			"work_title": "I'm Accepted",
			"work_artist": "Dana Key",
			"perf_title": "I'm Accepted",
			"perf_artist": "DeGarmo & Key",
			"release_year": "1989",
			"work_id": "W_181881",
			"perf_id": "P_675548",
			"yt_link": "http://www.youtube.com/embed/Xkd8_Utzb3I",
			"instrumental": "No"
		}
	},
	"W_181882": {},
	"W_181883": {
		"P_675553": {
			"work_title": "Boycott Hell",
			"work_artist": "Dana Key",
			"perf_title": "Boycott Hell",
			"perf_artist": "DeGarmo & Key",
			"release_year": "1989",
			"work_id": "W_181883",
			"perf_id": "P_675553",
			"yt_link": "http://www.youtube.com/embed/0CVZg89xuHY",
			"instrumental": "No"
		},
		"P_675554": {
			"work_title": "Boycott Hell",
			"work_artist": "Dana Key",
			"perf_title": "Boycott Hell",
			"perf_artist": "Newsboys",
			"release_year": "1991",
			"work_id": "W_181883",
			"perf_id": "P_675554",
			"yt_link": "http://www.youtube.com/embed/V6b1jptPuGs",
			"instrumental": "No"
		}
	},
	"W_181884": {
		"P_675560": {
			"work_title": "Listen to Our Hearts",
			"work_artist": "Geoff Moore",
			"perf_title": "Listen to Our Hearts",
			"perf_artist": "Geoff Moore and The Distance with Steven Curtis Chapman",
			"release_year": "1992",
			"work_id": "W_181884",
			"perf_id": "P_675560",
			"yt_link": "http://www.youtube.com/embed/f7dRb1fIl2M",
			"instrumental": "No"
		}
	},
	"W_181903": {
		"P_675793": {
			"work_title": "The Time in Between",
			"work_artist": "Mickey Jones",
			"perf_title": "The Time in Between",
			"perf_artist": "Cliff Richard and The Shadows",
			"release_year": "1965",
			"work_id": "W_181903",
			"perf_id": "P_675793",
			"yt_link": "http://www.youtube.com/embed/LUaiGz2YQTs",
			"instrumental": "No"
		}
	},
	"W_181910": {},
	"W_181926": {},
	"W_181929": {
		"P_675895": {
			"work_title": "Sensitivity",
			"work_artist": "Jimmy Jam",
			"perf_title": "Sensitivity",
			"perf_artist": "Ralph Tresvant",
			"release_year": "1990",
			"work_id": "W_181929",
			"perf_id": "P_675895",
			"yt_link": "http://www.youtube.com/embed/xhfhVSUCLY4",
			"instrumental": "No"
		},
		"P_675898": {
			"work_title": "Sensitivity",
			"work_artist": "Jimmy Jam",
			"perf_title": "Sensitivity",
			"perf_artist": "Meshell Ndeg\u00e9ocello",
			"release_year": "2018",
			"work_id": "W_181929",
			"perf_id": "P_675898",
			"yt_link": "http://www.youtube.com/embed/r3b9dPn3MPU",
			"instrumental": "No"
		}
	},
	"W_182128": {
		"P_677296": {
			"work_title": "Left Over Biscuits",
			"work_artist": "Harold Handy",
			"perf_title": "Left Over Biscuits",
			"perf_artist": "The Lost & Found [US1]",
			"release_year": "1980",
			"work_id": "W_182128",
			"perf_id": "P_677296",
			"yt_link": "http://www.youtube.com/embed/0glOJct4zcA",
			"instrumental": "No"
		}
	},
	"W_182131": {
		"P_677341": {
			"work_title": "You Are My One True Love",
			"work_artist": "Bob Kames",
			"perf_title": "Waltz Medley: Tales from the Vienna Woods / Blue Skirt Waltz / You Are My One True Love",
			"perf_artist": "Bobby Vinton",
			"release_year": "1976",
			"work_id": "W_182131",
			"perf_id": "P_677341",
			"yt_link": "http://www.youtube.com/embed/n3YowRPLL10",
			"instrumental": "No"
		}
	},
	"W_182132": {},
	"W_182133": {},
	"W_182134": {
		"P_677351": {
			"work_title": "Automaton",
			"work_artist": "Joe Pernice",
			"perf_title": "Automaton",
			"perf_artist": "Pernice Brothers",
			"release_year": "2006",
			"work_id": "W_182134",
			"perf_id": "P_677351",
			"yt_link": "http://www.youtube.com/embed/0ZWNp_Xy048",
			"instrumental": "No"
		}
	},
	"W_182135": {},
	"W_182136": {},
	"W_182137": {
		"P_677359": {
			"work_title": "Goodbye Dreaming Fields",
			"work_artist": "Martin Newell",
			"perf_title": "Goodbye Dreaming Fields",
			"perf_artist": "Martin Newell",
			"release_year": "1993",
			"work_id": "W_182137",
			"perf_id": "P_677359",
			"yt_link": "http://www.youtube.com/embed/6Uqa1rMZaic",
			"instrumental": "No"
		}
	},
	"W_182138": {},
	"W_182140": {
		"P_677392": {
			"work_title": "Lover",
			"work_artist": "Bryan Ferry",
			"perf_title": "Lover",
			"perf_artist": "Roxy Music",
			"release_year": "1980",
			"work_id": "W_182140",
			"perf_id": "P_677392",
			"yt_link": "http://www.youtube.com/embed/pHiHqEFkUkU",
			"instrumental": "No"
		},
		"P_677393": {
			"work_title": "Lover",
			"work_artist": "Bryan Ferry",
			"perf_title": "Lover",
			"perf_artist": "Nite Jewel",
			"release_year": "2009",
			"work_id": "W_182140",
			"perf_id": "P_677393",
			"yt_link": "http://www.youtube.com/embed/pkFLjN9Dntw",
			"instrumental": "No"
		}
	},
	"W_182141": {
		"P_677395": {
			"work_title": "Kamerasong",
			"work_artist": "Irmin Schmidt",
			"perf_title": "Kamera-Song",
			"perf_artist": "The Inner Space",
			"release_year": "1968",
			"work_id": "W_182141",
			"perf_id": "P_677395",
			"yt_link": "http://www.youtube.com/embed/Fq4VJ493vYg",
			"instrumental": "No"
		},
		"P_677397": {
			"work_title": "Kamerasong",
			"work_artist": "Irmin Schmidt",
			"perf_title": "Kamera Song",
			"perf_artist": "Nite Jewel",
			"release_year": "2009",
			"work_id": "W_182141",
			"perf_id": "P_677397",
			"yt_link": "http://www.youtube.com/embed/bK2J15H8DDM",
			"instrumental": "No"
		}
	},
	"W_182155": {
		"P_677464": {
			"work_title": "Little White Church",
			"work_artist": "Karen Fairchild",
			"perf_title": "Little White Church",
			"perf_artist": "Little Big Town",
			"release_year": "2010",
			"work_id": "W_182155",
			"perf_id": "P_677464",
			"yt_link": "http://www.youtube.com/embed/4FOC6-ES69k",
			"instrumental": "No"
		}
	},
	"W_182157": {},
	"W_182158": {
		"P_677589": {
			"work_title": "Bop! Goes My Heart",
			"work_artist": "Jule Styne",
			"perf_title": "Bop! Goes My Heart",
			"perf_artist": "Frank Sinatra and The Phil Moore Four",
			"release_year": "1949",
			"work_id": "W_182158",
			"perf_id": "P_677589",
			"yt_link": "http://www.youtube.com/embed/LRCUoLCUaCc",
			"instrumental": "No"
		}
	},
	"W_182160": {
		"P_677611": {
			"work_title": "From the Heart",
			"work_artist": "Ray Charles",
			"perf_title": "From the Heart",
			"perf_artist": "Ray Charles",
			"release_year": "1961",
			"work_id": "W_182160",
			"perf_id": "P_677611",
			"yt_link": "http://www.youtube.com/embed/Hz_mvFAhkAk",
			"instrumental": "Yes"
		}
	},
	"W_182161": {
		"P_677616": {
			"work_title": "Sherri",
			"work_artist": "Hank Crawford",
			"perf_title": "Sherri",
			"perf_artist": "Hank Crawford",
			"release_year": "1962",
			"work_id": "W_182161",
			"perf_id": "P_677616",
			"yt_link": "http://www.youtube.com/embed/8kbCJYR-Jg0",
			"instrumental": "Yes"
		}
	},
	"W_182166": {
		"P_677631": {
			"work_title": "Neem me in je armen",
			"work_artist": "Jean Kluger",
			"perf_title": "Neem me in je armen",
			"perf_artist": "Corry & Ronnie Tober",
			"release_year": "1986",
			"work_id": "W_182166",
			"perf_id": "P_677631",
			"yt_link": "http://www.youtube.com/embed/Ygk7K1b33aQ",
			"instrumental": "No"
		}
	},
	"W_182168": {
		"P_677636": {
			"work_title": "Meu Querido, Meu Velho, Meu Amigo",
			"work_artist": "Roberto Carlos",
			"perf_title": "Meu Querido, Meu Velho, Meu Amigo",
			"perf_artist": "Roberto Carlos",
			"release_year": "1979",
			"work_id": "W_182168",
			"perf_id": "P_677636",
			"yt_link": "http://www.youtube.com/embed/89x9JbbvL5U",
			"instrumental": "No"
		}
	},
	"W_182172": {},
	"W_182174": {
		"P_677665": {
			"work_title": "Il tempo se ne va",
			"work_artist": "Toto Cutugno",
			"perf_title": "Il tempo se ne va",
			"perf_artist": "Adriano Celentano",
			"release_year": "1980",
			"work_id": "W_182174",
			"perf_id": "P_677665",
			"yt_link": "http://www.youtube.com/embed/kPYBn8VcdXk",
			"instrumental": "No"
		}
	},
	"W_182186": {},
	"W_182188": {},
	"W_182195": {},
	"W_182213": {
		"P_678041": {
			"work_title": "Chicken Man [Theme from Grange Hill]",
			"work_artist": "Alan Hawkshaw",
			"perf_title": "Grange Hill (\"Chicken Man\")",
			"perf_artist": "Hawkshaw",
			"release_year": "1979",
			"work_id": "W_182213",
			"perf_id": "P_678041",
			"yt_link": "http://www.youtube.com/embed/IpKH7rUQ2rY",
			"instrumental": "Yes"
		},
		"P_678042": {
			"work_title": "Chicken Man [Theme from Grange Hill]",
			"work_artist": "Alan Hawkshaw",
			"perf_title": "Grange Hill",
			"perf_artist": "Dream Themes",
			"release_year": "2017",
			"work_id": "W_182213",
			"perf_id": "P_678042",
			"yt_link": "http://www.youtube.com/embed/tEW31_0D5VE",
			"instrumental": "Yes"
		}
	}
}