{
	"W_189802": {
		"P_717024": {
			"work_title": "No podr\u00e1s",
			"work_artist": "Peter Skrabak",
			"perf_title": "No podr\u00e1s",
			"perf_artist": "Cristian Castro",
			"release_year": "1992",
			"work_id": "W_189802",
			"perf_id": "P_717024",
			"yt_link": "http://www.youtube.com/embed/JIfm1sZi-Zw",
			"instrumental": "No"
		},
		"P_717025": {
			"work_title": "No podr\u00e1s",
			"work_artist": "Peter Skrabak",
			"perf_title": "No podr\u00e1s",
			"perf_artist": "Fernando Villalona",
			"release_year": "1993",
			"work_id": "W_189802",
			"perf_id": "P_717025",
			"yt_link": "http://www.youtube.com/embed/ZAH8LIDYq_w",
			"instrumental": "No"
		}
	},
	"W_189805": {
		"P_717033": {
			"work_title": "Baby Blue",
			"work_artist": "Samuel Gulino",
			"perf_title": "Baby Blue",
			"perf_artist": "The Echoes [US3]",
			"release_year": "1961",
			"work_id": "W_189805",
			"perf_id": "P_717033",
			"yt_link": "http://www.youtube.com/embed/n1hVMHJgBgI",
			"instrumental": "No"
		}
	},
	"W_189814": {},
	"W_189816": {
		"P_717052": {
			"work_title": "Blind",
			"work_artist": "Charlie Colin",
			"perf_title": "Blind",
			"perf_artist": "Train",
			"release_year": "1996",
			"work_id": "W_189816",
			"perf_id": "P_717052",
			"yt_link": "http://www.youtube.com/embed/Gz2AYmcDpAE",
			"instrumental": "No"
		},
		"P_717054": {
			"work_title": "Blind",
			"work_artist": "Charlie Colin",
			"perf_title": "Blind [Train]",
			"perf_artist": "Vitamin String Quartet",
			"release_year": "2003",
			"work_id": "W_189816",
			"perf_id": "P_717054",
			"yt_link": "http://www.youtube.com/embed/boteVhm7s-Q",
			"instrumental": "Yes"
		}
	},
	"W_189817": {
		"P_717055": {
			"work_title": "I Am",
			"work_artist": "Rob Hotchkiss",
			"perf_title": "I Am",
			"perf_artist": "Train",
			"release_year": "1996",
			"work_id": "W_189817",
			"perf_id": "P_717055",
			"yt_link": "http://www.youtube.com/embed/hPYdCL2dl1Y",
			"instrumental": "No"
		}
	},
	"W_189818": {
		"P_717057": {
			"work_title": "Mississippi",
			"work_artist": "Charlie Colin",
			"perf_title": "Mississippi",
			"perf_artist": "Train",
			"release_year": "2001",
			"work_id": "W_189818",
			"perf_id": "P_717057",
			"yt_link": "http://www.youtube.com/embed/uMjS1xzySps",
			"instrumental": "No"
		},
		"P_717058": {
			"work_title": "Mississippi",
			"work_artist": "Charlie Colin",
			"perf_title": "Mississippi",
			"perf_artist": "Vitamin String Quartet",
			"release_year": "2003",
			"work_id": "W_189818",
			"perf_id": "P_717058",
			"yt_link": "http://www.youtube.com/embed/NL4pANL7Tr0",
			"instrumental": "Yes"
		}
	},
	"W_189819": {
		"P_717059": {
			"work_title": "I Wish You Would",
			"work_artist": "Charlie Colin",
			"perf_title": "I Wish You Would",
			"perf_artist": "Train",
			"release_year": "2001",
			"work_id": "W_189819",
			"perf_id": "P_717059",
			"yt_link": "http://www.youtube.com/embed/PdXw_bM4COU",
			"instrumental": "No"
		}
	},
	"W_189820": {
		"P_717061": {
			"work_title": "Heavy",
			"work_artist": "Charlie Colin",
			"perf_title": "Heavy",
			"perf_artist": "Train",
			"release_year": "1996",
			"work_id": "W_189820",
			"perf_id": "P_717061",
			"yt_link": "http://www.youtube.com/embed/bLWkt-y8UAY",
			"instrumental": "No"
		},
		"P_717063": {
			"work_title": "Heavy",
			"work_artist": "Charlie Colin",
			"perf_title": "Heavy [Train]",
			"perf_artist": "Vitamin String Quartet",
			"release_year": "2003",
			"work_id": "W_189820",
			"perf_id": "P_717063",
			"yt_link": "http://www.youtube.com/embed/KKOtNm0R5Sc",
			"instrumental": "Yes"
		}
	},
	"W_189828": {
		"P_717100": {
			"work_title": "\u3053\u308c\u306f\u604b\u3067\u306f\u306a\u3044 [This Can't Be Love]",
			"work_artist": "Yasuharu Konishi",
			"perf_title": "\u3053\u308c\u306f\u604b\u3067\u306f\u306a\u3044 [This Can't Be Love]",
			"perf_artist": "Pizzicato Five",
			"release_year": "1988",
			"work_id": "W_189828",
			"perf_id": "P_717100",
			"yt_link": "http://www.youtube.com/embed/5mQIlbOjLjM",
			"instrumental": "No"
		},
		"P_717101": {
			"work_title": "\u3053\u308c\u306f\u604b\u3067\u306f\u306a\u3044 [This Can't Be Love]",
			"work_artist": "Yasuharu Konishi",
			"perf_title": "\u3053\u308c\u306f\u604b\u3067\u306f\u306a\u3044 [This Can't Be Love]",
			"perf_artist": "Mihiro",
			"release_year": "2009",
			"work_id": "W_189828",
			"perf_id": "P_717101",
			"yt_link": "http://www.youtube.com/embed/7w5PlGweiGM",
			"instrumental": "No"
		}
	},
	"W_189833": {
		"P_717131": {
			"work_title": "Oden Ride over Nordland",
			"work_artist": "Quorthon",
			"perf_title": "Odens Ride over Nordland - A Fine Day to Die",
			"perf_artist": "Order of the Ebon Hand",
			"release_year": "1997",
			"work_id": "W_189833",
			"perf_id": "P_717131",
			"yt_link": "http://www.youtube.com/embed/m0Epacjiw2s",
			"instrumental": "No"
		}
	},
	"W_189834": {
		"P_717141": {
			"work_title": "I Don't Want Nobody to Give me Nothing",
			"work_artist": "James Brown",
			"perf_title": "I Don't Want Nobody to Give Me Nothing (Open Up the Door, I'll Get it Myself)",
			"perf_artist": "James Brown",
			"release_year": "1969",
			"work_id": "W_189834",
			"perf_id": "P_717141",
			"yt_link": "http://www.youtube.com/embed/aRclVQvidxg",
			"instrumental": "No"
		},
		"P_762582": {
			"work_title": "I Don't Want Nobody to Give me Nothing",
			"work_artist": "James Brown",
			"perf_title": "I Don't Want Nobody to Give me Nothing",
			"perf_artist": "Phil Upchurch",
			"release_year": "1992",
			"work_id": "W_189834",
			"perf_id": "P_762582",
			"yt_link": "http://www.youtube.com/embed/4TgXwacGGLM",
			"instrumental": "No"
		}
	},
	"W_189837": {
		"P_717140": {
			"work_title": "Father to Son",
			"work_artist": "Quorthon",
			"perf_title": "Father to Son",
			"perf_artist": "Bathory",
			"release_year": "1990",
			"work_id": "W_189837",
			"perf_id": "P_717140",
			"yt_link": "http://www.youtube.com/embed/qFheVvdFmaw",
			"instrumental": "No"
		},
		"P_717142": {
			"work_title": "Father to Son",
			"work_artist": "Quorthon",
			"perf_title": "Father to Son",
			"perf_artist": "Brain Fade",
			"release_year": "1997",
			"work_id": "W_189837",
			"perf_id": "P_717142",
			"yt_link": "http://www.youtube.com/embed/mfJTlraRhxc",
			"instrumental": "No"
		}
	},
	"W_189838": {},
	"W_189839": {
		"P_717150": {
			"work_title": "Pushin' Up Daisies",
			"work_artist": "John Hadley",
			"perf_title": "Pushing Up Daisies",
			"perf_artist": "Vitamin String Quartet",
			"release_year": "2003",
			"work_id": "W_189839",
			"perf_id": "P_717150",
			"yt_link": "http://www.youtube.com/embed/ZanOqirPXUQ",
			"instrumental": "Yes"
		}
	},
	"W_189842": {
		"P_717175": {
			"work_title": "Some Things You Never Get Used To",
			"work_artist": "Nickolas Ashford",
			"perf_title": "Some Things You Never Get Used To",
			"perf_artist": "Diana Ross and The Supremes",
			"release_year": "1968",
			"work_id": "W_189842",
			"perf_id": "P_717175",
			"yt_link": "http://www.youtube.com/embed/AFzoE1MVmpg",
			"instrumental": "No"
		},
		"P_717176": {
			"work_title": "Some Things You Never Get Used To",
			"work_artist": "Nickolas Ashford",
			"perf_title": "Some Things You Never Get Used To",
			"perf_artist": "Frances Nero",
			"release_year": "1990",
			"work_id": "W_189842",
			"perf_id": "P_717176",
			"yt_link": "http://www.youtube.com/embed/qMH0_cr-GIo",
			"instrumental": "No"
		}
	},
	"W_189843": {
		"P_717178": {
			"work_title": "Plague Rages",
			"work_artist": "Shane Embury",
			"perf_title": "Plague Rages",
			"perf_artist": "Napalm Death",
			"release_year": "1994",
			"work_id": "W_189843",
			"perf_id": "P_717178",
			"yt_link": "http://www.youtube.com/embed/lzLTh7kMz58",
			"instrumental": "No"
		}
	},
	"W_189844": {
		"P_717181": {
			"work_title": "Antibody",
			"work_artist": "Shane Embury",
			"perf_title": "Antibody",
			"perf_artist": "Napalm Death",
			"release_year": "1995",
			"work_id": "W_189844",
			"perf_id": "P_717181",
			"yt_link": "http://www.youtube.com/embed/OJPhetmYYA8",
			"instrumental": "No"
		}
	},
	"W_189845": {
		"P_717183": {
			"work_title": "Next on the List",
			"work_artist": "Shane Embury",
			"perf_title": "Next on the List",
			"perf_artist": "Napalm Death",
			"release_year": "2000",
			"work_id": "W_189845",
			"perf_id": "P_717183",
			"yt_link": "http://www.youtube.com/embed/5YHjFYTwICQ",
			"instrumental": "No"
		}
	},
	"W_189846": {
		"P_717184": {
			"work_title": "Pay for the Privilege of Breathing",
			"work_artist": "Shane Embury",
			"perf_title": "Pay for the Privilege of Breathing",
			"perf_artist": "Napalm Death",
			"release_year": "2005",
			"work_id": "W_189846",
			"perf_id": "P_717184",
			"yt_link": "http://www.youtube.com/embed/gEYNsqCBj4k",
			"instrumental": "No"
		},
		"P_717185": {
			"work_title": "Pay for the Privilege of Breathing",
			"work_artist": "Shane Embury",
			"perf_title": "Pay for the Privilege of Breathing",
			"perf_artist": "Japura Noise Project",
			"release_year": "2013",
			"work_id": "W_189846",
			"perf_id": "P_717185",
			"yt_link": "http://www.youtube.com/embed/RhgKQWV0d1s",
			"instrumental": "No"
		}
	},
	"W_189847": {
		"P_717186": {
			"work_title": "Warped Beyond Logic",
			"work_artist": "Shane Embury",
			"perf_title": "Warped Beyond Logic",
			"perf_artist": "Napalm Death",
			"release_year": "2006",
			"work_id": "W_189847",
			"perf_id": "P_717186",
			"yt_link": "http://www.youtube.com/embed/EHUZITt0WrI",
			"instrumental": "No"
		},
		"P_717187": {
			"work_title": "Warped Beyond Logic",
			"work_artist": "Shane Embury",
			"perf_title": "Warped Beyond Logic",
			"perf_artist": "Obitto",
			"release_year": "2013",
			"work_id": "W_189847",
			"perf_id": "P_717187",
			"yt_link": "http://www.youtube.com/embed/aSQpdFPQrcQ",
			"instrumental": "No"
		}
	},
	"W_189848": {
		"P_717188": {
			"work_title": "Siege of Power",
			"work_artist": "Justin Broadrick",
			"perf_title": "Siege of Power",
			"perf_artist": "Napalm Death",
			"release_year": "1987",
			"work_id": "W_189848",
			"perf_id": "P_717188",
			"yt_link": "http://www.youtube.com/embed/M0yEt5qI3z0",
			"instrumental": "No"
		},
		"P_717189": {
			"work_title": "Siege of Power",
			"work_artist": "Justin Broadrick",
			"perf_title": "Siege of Power",
			"perf_artist": "Oligarquia",
			"release_year": "2013",
			"work_id": "W_189848",
			"perf_id": "P_717189",
			"yt_link": "http://www.youtube.com/embed/jT7Y-GvLCKE",
			"instrumental": "No"
		}
	},
	"W_189849": {
		"P_717192": {
			"work_title": "On the Brink of Extinction",
			"work_artist": "Shane Embury",
			"perf_title": "On the Brink of Extinction",
			"perf_artist": "Napalm Death",
			"release_year": "2009",
			"work_id": "W_189849",
			"perf_id": "P_717192",
			"yt_link": "http://www.youtube.com/embed/npa8qUNEIFY",
			"instrumental": "No"
		}
	},
	"W_189850": {
		"P_717194": {
			"work_title": "Right You Are",
			"work_artist": "Shane Embury",
			"perf_title": "Right You Are",
			"perf_artist": "Napalm Death",
			"release_year": "2005",
			"work_id": "W_189850",
			"perf_id": "P_717194",
			"yt_link": "http://www.youtube.com/embed/KFQUI7-7amA",
			"instrumental": "No"
		}
	},
	"W_189851": {
		"P_717196": {
			"work_title": "No One Gets the Prize",
			"work_artist": "Nickolas Ashford",
			"perf_title": "No One Gets the Prize",
			"perf_artist": "Diana Ross",
			"release_year": "1979",
			"work_id": "W_189851",
			"perf_id": "P_717196",
			"yt_link": "http://www.youtube.com/embed/SqudwtdZscA",
			"instrumental": "No"
		},
		"P_717198": {
			"work_title": "No One Gets the Prize",
			"work_artist": "Nickolas Ashford",
			"perf_title": "No One Gets the Prize",
			"perf_artist": "Earl Van Dyke",
			"release_year": "1996",
			"work_id": "W_189851",
			"perf_id": "P_717198",
			"yt_link": "http://www.youtube.com/embed/6gxM6KcNNJ8",
			"instrumental": "No"
		}
	},
	"W_189852": {
		"P_717195": {
			"work_title": "Silence is Deafening",
			"work_artist": "Jesse Pintado",
			"perf_title": "Silence is Deafening",
			"perf_artist": "Napalm Death",
			"release_year": "2005",
			"work_id": "W_189852",
			"perf_id": "P_717195",
			"yt_link": "http://www.youtube.com/embed/bsNaALbbo7Q",
			"instrumental": "No"
		}
	},
	"W_189853": {
		"P_717200": {
			"work_title": "Inside the Torn Apart",
			"work_artist": "Shane Embury",
			"perf_title": "Inside the Torn Apart",
			"perf_artist": "Napalm Death",
			"release_year": "1997",
			"work_id": "W_189853",
			"perf_id": "P_717200",
			"yt_link": "http://www.youtube.com/embed/VmveEWHRuq8",
			"instrumental": "No"
		}
	},
	"W_189860": {
		"P_717271": {
			"work_title": "Beneath, Between and Behind",
			"work_artist": "Neil Peart",
			"perf_title": "Beneath, Between and Behind",
			"perf_artist": "Rush",
			"release_year": "1975",
			"work_id": "W_189860",
			"perf_id": "P_717271",
			"yt_link": "http://www.youtube.com/embed/xjAlW4r9mAg",
			"instrumental": "No"
		},
		"P_717272": {
			"work_title": "Beneath, Between and Behind",
			"work_artist": "Neil Peart",
			"perf_title": "Beneath, Between & Behind",
			"perf_artist": "Vitamin String Quartet",
			"release_year": "2002",
			"work_id": "W_189860",
			"perf_id": "P_717272",
			"yt_link": "http://www.youtube.com/embed/s7BSTfyn-uU",
			"instrumental": "Yes"
		}
	},
	"W_189862": {
		"P_717274": {
			"work_title": "Broon's Bane",
			"work_artist": "Alex Lifeson",
			"perf_title": "Broon's Bane",
			"perf_artist": "Vitamin String Quartet",
			"release_year": "2002",
			"work_id": "W_189862",
			"perf_id": "P_717274",
			"yt_link": "http://www.youtube.com/embed/58jJwKRxiZg",
			"instrumental": "Yes"
		}
	},
	"W_189864": {
		"P_717296": {
			"work_title": "Wind on the Water",
			"work_artist": "Graham Nash",
			"perf_title": "Wind on the Water",
			"perf_artist": "David Crosby/Graham Nash",
			"release_year": "1975",
			"work_id": "W_189864",
			"perf_id": "P_717296",
			"yt_link": "http://www.youtube.com/embed/1f7d5NvJj9s",
			"instrumental": "No"
		}
	},
	"W_189870": {
		"P_717305": {
			"work_title": "Lonestar",
			"work_artist": "Lee Alexander",
			"perf_title": "Lonestar",
			"perf_artist": "Norah Jones",
			"release_year": "2002",
			"work_id": "W_189870",
			"perf_id": "P_717305",
			"yt_link": "http://www.youtube.com/embed/0_LNkrlm7T0",
			"instrumental": "No"
		},
		"P_717306": {
			"work_title": "Lonestar",
			"work_artist": "Lee Alexander",
			"perf_title": "Lonestar",
			"perf_artist": "Vitamin String Quartet",
			"release_year": "2003",
			"work_id": "W_189870",
			"perf_id": "P_717306",
			"yt_link": "http://www.youtube.com/embed/i_ZI8sDLQxw",
			"instrumental": "Yes"
		}
	},
	"W_189871": {
		"P_717307": {
			"work_title": "Painter Song",
			"work_artist": "Gerald Clinton Hopson",
			"perf_title": "Painter Song",
			"perf_artist": "Norah Jones",
			"release_year": "2002",
			"work_id": "W_189871",
			"perf_id": "P_717307",
			"yt_link": "http://www.youtube.com/embed/A6AtIxSiCHU",
			"instrumental": "No"
		},
		"P_717308": {
			"work_title": "Painter Song",
			"work_artist": "Gerald Clinton Hopson",
			"perf_title": "If I Were a Painter",
			"perf_artist": "Vitamin String Quartet",
			"release_year": "2003",
			"work_id": "W_189871",
			"perf_id": "P_717308",
			"yt_link": "http://www.youtube.com/embed/CbjoPfufAMs",
			"instrumental": "Yes"
		}
	},
	"W_189872": {
		"P_717309": {
			"work_title": "Seven Years",
			"work_artist": "Lee Alexander",
			"perf_title": "Seven Years",
			"perf_artist": "Norah Jones",
			"release_year": "2002",
			"work_id": "W_189872",
			"perf_id": "P_717309",
			"yt_link": "http://www.youtube.com/embed/UI7hkrAoulU",
			"instrumental": "No"
		},
		"P_717311": {
			"work_title": "Seven Years",
			"work_artist": "Lee Alexander",
			"perf_title": "Seven Years",
			"perf_artist": "Vitamin String Quartet",
			"release_year": "2003",
			"work_id": "W_189872",
			"perf_id": "P_717311",
			"yt_link": "http://www.youtube.com/embed/huL_UAfO02c",
			"instrumental": "Yes"
		}
	},
	"W_189875": {
		"P_717319": {
			"work_title": "Down So Long",
			"work_artist": "Jewel",
			"perf_title": "Down So Long",
			"perf_artist": "Jewel",
			"release_year": "1998",
			"work_id": "W_189875",
			"perf_id": "P_717319",
			"yt_link": "http://www.youtube.com/embed/zH5bC2jTluM",
			"instrumental": "No"
		},
		"P_717320": {
			"work_title": "Down So Long",
			"work_artist": "Jewel",
			"perf_title": "Down So Long",
			"perf_artist": "Vitamin String Quartet",
			"release_year": "2003",
			"work_id": "W_189875",
			"perf_id": "P_717320",
			"yt_link": "http://www.youtube.com/embed/1nsw45Izo3g",
			"instrumental": "Yes"
		}
	},
	"W_189876": {
		"P_717321": {
			"work_title": "The New Wild West",
			"work_artist": "Jewel",
			"perf_title": "The New Wild West",
			"perf_artist": "Jewel",
			"release_year": "2001",
			"work_id": "W_189876",
			"perf_id": "P_717321",
			"yt_link": "http://www.youtube.com/embed/WGoJ4dIx4Ss",
			"instrumental": "No"
		}
	},
	"W_189877": {
		"P_717323": {
			"work_title": "What's Simple Is True",
			"work_artist": "Jewel",
			"perf_title": "What's Simple Is True",
			"perf_artist": "Jewel",
			"release_year": "1998",
			"work_id": "W_189877",
			"perf_id": "P_717323",
			"yt_link": "http://www.youtube.com/embed/U13Hx8pEtBM",
			"instrumental": "No"
		},
		"P_717324": {
			"work_title": "What's Simple Is True",
			"work_artist": "Jewel",
			"perf_title": "What's Simple Is True",
			"perf_artist": "Vitamin String Quartet",
			"release_year": "2003",
			"work_id": "W_189877",
			"perf_id": "P_717324",
			"yt_link": "http://www.youtube.com/embed/gXZMKLX_NUw",
			"instrumental": "Yes"
		}
	},
	"W_189878": {
		"P_717325": {
			"work_title": "Absence of Fear",
			"work_artist": "Jewel",
			"perf_title": "Absence of Fear",
			"perf_artist": "Jewel",
			"release_year": "1998",
			"work_id": "W_189878",
			"perf_id": "P_717325",
			"yt_link": "http://www.youtube.com/embed/BRf6RxaJexI",
			"instrumental": "No"
		},
		"P_717326": {
			"work_title": "Absence of Fear",
			"work_artist": "Jewel",
			"perf_title": "Absence of Fear",
			"perf_artist": "Vitamin String Quartet",
			"release_year": "2003",
			"work_id": "W_189878",
			"perf_id": "P_717326",
			"yt_link": "http://www.youtube.com/embed/swCT8CQHaOU",
			"instrumental": "Yes"
		}
	},
	"W_189880": {
		"P_717346": {
			"work_title": "Sarah Yellin'",
			"work_artist": "Brad Arnold",
			"perf_title": "Sarah Yellin'",
			"perf_artist": "3 Doors Down",
			"release_year": "2002",
			"work_id": "W_189880",
			"perf_id": "P_717346",
			"yt_link": "http://www.youtube.com/embed/Zd8C_5ZXyzo",
			"instrumental": "No"
		},
		"P_717348": {
			"work_title": "Sarah Yellin'",
			"work_artist": "Brad Arnold",
			"perf_title": "Sarah Yellin'",
			"perf_artist": "Vitamin String Quartet",
			"release_year": "2003",
			"work_id": "W_189880",
			"perf_id": "P_717348",
			"yt_link": "http://www.youtube.com/embed/9Tk_Rdcj5zg",
			"instrumental": "Yes"
		}
	},
	"W_189881": {
		"P_717350": {
			"work_title": "Ex-Girlfriend",
			"work_artist": "Tom Dumont",
			"perf_title": "Ex-Girlfriend",
			"perf_artist": "No Doubt",
			"release_year": "2000",
			"work_id": "W_189881",
			"perf_id": "P_717350",
			"yt_link": "http://www.youtube.com/embed/8Yqru5UXWGY",
			"instrumental": "No"
		},
		"P_717403": {
			"work_title": "Ex-Girlfriend",
			"work_artist": "Tom Dumont",
			"perf_title": "Ex Girlfriend",
			"perf_artist": "Vitamin String Quartet",
			"release_year": "2003",
			"work_id": "W_189881",
			"perf_id": "P_717403",
			"yt_link": "http://www.youtube.com/embed/_o1Jt6dMUSU",
			"instrumental": "Yes"
		}
	},
	"W_189882": {
		"P_717352": {
			"work_title": "Going Down in Flames",
			"work_artist": "Brad Arnold",
			"perf_title": "Going Down in Flames",
			"perf_artist": "3 Doors Down",
			"release_year": "2002",
			"work_id": "W_189882",
			"perf_id": "P_717352",
			"yt_link": "http://www.youtube.com/embed/BHvqZVwpI9o",
			"instrumental": "No"
		},
		"P_717353": {
			"work_title": "Going Down in Flames",
			"work_artist": "Brad Arnold",
			"perf_title": "Going Down in Flames",
			"perf_artist": "Vitamin String Quartet",
			"release_year": "2003",
			"work_id": "W_189882",
			"perf_id": "P_717353",
			"yt_link": "http://www.youtube.com/embed/TRLkvNL87HQ",
			"instrumental": "Yes"
		}
	},
	"W_189883": {
		"P_717357": {
			"work_title": "Better Life",
			"work_artist": "Brad Arnold",
			"perf_title": "Better Life",
			"perf_artist": "3 Doors Down",
			"release_year": "2000",
			"work_id": "W_189883",
			"perf_id": "P_717357",
			"yt_link": "http://www.youtube.com/embed/4clQPRTsh8Q",
			"instrumental": "No"
		},
		"P_717358": {
			"work_title": "Better Life",
			"work_artist": "Brad Arnold",
			"perf_title": "Better Life",
			"perf_artist": "Vitamin String Quartet",
			"release_year": "2003",
			"work_id": "W_189883",
			"perf_id": "P_717358",
			"yt_link": "http://www.youtube.com/embed/aeEhFUoIGDM",
			"instrumental": "Yes"
		}
	},
	"W_189884": {
		"P_717359": {
			"work_title": "By My Side",
			"work_artist": "Brad Arnold",
			"perf_title": "By My Side",
			"perf_artist": "3 Doors Down",
			"release_year": "2000",
			"work_id": "W_189884",
			"perf_id": "P_717359",
			"yt_link": "http://www.youtube.com/embed/MbpTHFtMzDQ",
			"instrumental": "No"
		},
		"P_717360": {
			"work_title": "By My Side",
			"work_artist": "Brad Arnold",
			"perf_title": "By My Side",
			"perf_artist": "Vitamin String Quartet",
			"release_year": "2003",
			"work_id": "W_189884",
			"perf_id": "P_717360",
			"yt_link": "http://www.youtube.com/embed/FNVSVeozkk4",
			"instrumental": "Yes"
		}
	},
	"W_189983": {
		"P_717751": {
			"work_title": "\u590f\u306a\u3093\u3060\u3057 {Natsu-nandashi}",
			"work_artist": "Yasuharu Konishi",
			"perf_title": "\u590f\u306a\u3093\u3060\u3057 {Natsu-nandashi}",
			"perf_artist": "Michiru Hoshino",
			"release_year": "2015",
			"work_id": "W_189983",
			"perf_id": "P_717751",
			"yt_link": "http://www.youtube.com/embed/gGkNYCQZKN4",
			"instrumental": "No"
		}
	},
	"W_189984": {
		"P_717753": {
			"work_title": "\u30a2\u30a4\u30c9\u30eb\u3070\u304b\u308a\u8074\u304b\u306a\u3044\u3067 {Idol bakari kikanaide}",
			"work_artist": "Yasuharu Konishi",
			"perf_title": "\u30a2\u30a4\u30c9\u30eb\u3070\u304b\u308a\u8074\u304b\u306a\u3044\u3067 {Idol bakari kikanaide}",
			"perf_artist": "Negicco",
			"release_year": "2013",
			"work_id": "W_189984",
			"perf_id": "P_717753",
			"yt_link": "http://www.youtube.com/embed/bo_7NrSqmIE",
			"instrumental": "No"
		}
	},
	"W_189988": {
		"P_717769": {
			"work_title": "Life's About to Get Good",
			"work_artist": "Shania Twain",
			"perf_title": "Life's About to Get Good",
			"perf_artist": "Shania Twain",
			"release_year": "2017",
			"work_id": "W_189988",
			"perf_id": "P_717769",
			"yt_link": "http://www.youtube.com/embed/we-VfNnbzzY",
			"instrumental": "No"
		}
	},
	"W_189989": {
		"P_717771": {
			"work_title": "Swingin' with My Eyes Closed",
			"work_artist": "Shania Twain",
			"perf_title": "Swingin' with My Eyes Closed",
			"perf_artist": "Shania Twain",
			"release_year": "2017",
			"work_id": "W_189989",
			"perf_id": "P_717771",
			"yt_link": "http://www.youtube.com/embed/zmg9tVaMVd4",
			"instrumental": "No"
		}
	},
	"W_189990": {
		"P_717775": {
			"work_title": "Today Is Your Day",
			"work_artist": "Shania Twain",
			"perf_title": "Today Is Your Day",
			"perf_artist": "Shania Twain",
			"release_year": "2011",
			"work_id": "W_189990",
			"perf_id": "P_717775",
			"yt_link": "http://www.youtube.com/embed/fg490hneE5k",
			"instrumental": "No"
		},
		"P_717776": {
			"work_title": "Today Is Your Day",
			"work_artist": "Shania Twain",
			"perf_title": "Today Is Your Day",
			"perf_artist": "Piano Dreamers",
			"release_year": "2017",
			"work_id": "W_189990",
			"perf_id": "P_717776",
			"yt_link": "http://www.youtube.com/embed/CbmDMXWt3qk",
			"instrumental": "Yes"
		}
	},
	"W_189991": {
		"P_717783": {
			"work_title": "Mourir demain",
			"work_artist": "Asdorve",
			"perf_title": "Mourir demain",
			"perf_artist": "Natasha St-Pier - Pascal Obispo",
			"release_year": "2003",
			"work_id": "W_189991",
			"perf_id": "P_717783",
			"yt_link": "http://www.youtube.com/embed/KZEVTPN1hvo",
			"instrumental": "No"
		}
	},
	"W_189992": {
		"P_717791": {
			"work_title": "Toi et moi",
			"work_artist": "Guillaume Grand",
			"perf_title": "Toi et moi",
			"perf_artist": "Guillaume Grand",
			"release_year": "2010",
			"work_id": "W_189992",
			"perf_id": "P_717791",
			"yt_link": "http://www.youtube.com/embed/QLNr3_YNeJc",
			"instrumental": "No"
		},
		"P_717792": {
			"work_title": "Toi et moi",
			"work_artist": "Guillaume Grand",
			"perf_title": "Toi et moi",
			"perf_artist": "Aude Henneville",
			"release_year": "2012",
			"work_id": "W_189992",
			"perf_id": "P_717792",
			"yt_link": "http://www.youtube.com/embed/PoTEyNnYihk",
			"instrumental": "No"
		}
	},
	"W_189993": {
		"P_717822": {
			"work_title": "I'm Ready",
			"work_artist": "Adam Met",
			"perf_title": "I'm Ready",
			"perf_artist": "AJR",
			"release_year": "2013",
			"work_id": "W_189993",
			"perf_id": "P_717822",
			"yt_link": "http://www.youtube.com/embed/f2dJxFIV28Y",
			"instrumental": "No"
		},
		"P_717823": {
			"work_title": "I'm Ready",
			"work_artist": "Adam Met",
			"perf_title": "I'm Ready",
			"perf_artist": "Piano Tribute Players",
			"release_year": "2014",
			"work_id": "W_189993",
			"perf_id": "P_717823",
			"yt_link": "http://www.youtube.com/embed/0LCMFmoKNag",
			"instrumental": "Yes"
		}
	},
	"W_189998": {
		"P_717837": {
			"work_title": "Breakable",
			"work_artist": "Ingrid Michaelson",
			"perf_title": "Breakable",
			"perf_artist": "Ingrid Michaelson",
			"release_year": "2006",
			"work_id": "W_189998",
			"perf_id": "P_717837",
			"yt_link": "http://www.youtube.com/embed/YZjwdS_rmIE",
			"instrumental": "No"
		},
		"P_717838": {
			"work_title": "Breakable",
			"work_artist": "Ingrid Michaelson",
			"perf_title": "Breakable",
			"perf_artist": "Piano Tribute Players",
			"release_year": "2014",
			"work_id": "W_189998",
			"perf_id": "P_717838",
			"yt_link": "http://www.youtube.com/embed/HWPdn-Zpkqs",
			"instrumental": "Yes"
		}
	},
	"W_189999": {
		"P_717839": {
			"work_title": "You and I",
			"work_artist": "Ingrid Michaelson",
			"perf_title": "You and I",
			"perf_artist": "Ingrid Michaelson",
			"release_year": "2008",
			"work_id": "W_189999",
			"perf_id": "P_717839",
			"yt_link": "http://www.youtube.com/embed/XdEN1b-dwlw",
			"instrumental": "No"
		},
		"P_717841": {
			"work_title": "You and I",
			"work_artist": "Ingrid Michaelson",
			"perf_title": "You and I [Ingrid Michaelson]",
			"perf_artist": "Piano Tribute Players",
			"release_year": "2014",
			"work_id": "W_189999",
			"perf_id": "P_717841",
			"yt_link": "http://www.youtube.com/embed/75_j6MeliL4",
			"instrumental": "Yes"
		}
	},
	"W_190000": {
		"P_717842": {
			"work_title": "Afterlife",
			"work_artist": "Adam Pallin",
			"perf_title": "Afterlife",
			"perf_artist": "Ingrid Michaelson",
			"release_year": "2014",
			"work_id": "W_190000",
			"perf_id": "P_717842",
			"yt_link": "http://www.youtube.com/embed/uf_QhUZX3BM",
			"instrumental": "No"
		},
		"P_717844": {
			"work_title": "Afterlife",
			"work_artist": "Adam Pallin",
			"perf_title": "Afterlife [Ingrid Michaelson]",
			"perf_artist": "Piano Tribute Players",
			"release_year": "2014",
			"work_id": "W_190000",
			"perf_id": "P_717844",
			"yt_link": "http://www.youtube.com/embed/25xCElvMDBU",
			"instrumental": "Yes"
		}
	},
	"W_190001": {
		"P_717846": {
			"work_title": "Be OK",
			"work_artist": "Ingrid Michaelson",
			"perf_title": "Be OK",
			"perf_artist": "Ingrid Michaelson",
			"release_year": "2008",
			"work_id": "W_190001",
			"perf_id": "P_717846",
			"yt_link": "http://www.youtube.com/embed/vpMI8Qu5fsc",
			"instrumental": "No"
		},
		"P_717847": {
			"work_title": "Be OK",
			"work_artist": "Ingrid Michaelson",
			"perf_title": "Be OK",
			"perf_artist": "Piano Tribute Players",
			"release_year": "2014",
			"work_id": "W_190001",
			"perf_id": "P_717847",
			"yt_link": "http://www.youtube.com/embed/t62-EQEadmY",
			"instrumental": "Yes"
		}
	},
	"W_190002": {
		"P_717850": {
			"work_title": "Everybody",
			"work_artist": "Ingrid Michaelson",
			"perf_title": "Everybody",
			"perf_artist": "Ingrid Michaelson",
			"release_year": "2009",
			"work_id": "W_190002",
			"perf_id": "P_717850",
			"yt_link": "http://www.youtube.com/embed/TlFCfkyuQM0",
			"instrumental": "No"
		},
		"P_717851": {
			"work_title": "Everybody",
			"work_artist": "Ingrid Michaelson",
			"perf_title": "Everybody",
			"perf_artist": "Piano Tribute Players",
			"release_year": "2014",
			"work_id": "W_190002",
			"perf_id": "P_717851",
			"yt_link": "http://www.youtube.com/embed/N2oKxMoKjXc",
			"instrumental": "Yes"
		}
	},
	"W_190004": {
		"P_717864": {
			"work_title": "Maybe",
			"work_artist": "Ingrid Michaelson",
			"perf_title": "Maybe",
			"perf_artist": "Ingrid Michaelson",
			"release_year": "2009",
			"work_id": "W_190004",
			"perf_id": "P_717864",
			"yt_link": "http://www.youtube.com/embed/FKU3UuJhIxU",
			"instrumental": "No"
		},
		"P_717867": {
			"work_title": "Maybe",
			"work_artist": "Ingrid Michaelson",
			"perf_title": "Maybe [Ingrid Michaelson]",
			"perf_artist": "Piano Tribute Players",
			"release_year": "2014",
			"work_id": "W_190004",
			"perf_id": "P_717867",
			"yt_link": "http://www.youtube.com/embed/4ipXxVadGng",
			"instrumental": "Yes"
		}
	},
	"W_190005": {
		"P_717872": {
			"work_title": "Girls Chase Boys",
			"work_artist": "Trent Dabbs",
			"perf_title": "Girls Chase Boys",
			"perf_artist": "Ingrid Michaelson",
			"release_year": "2014",
			"work_id": "W_190005",
			"perf_id": "P_717872",
			"yt_link": "http://www.youtube.com/embed/5GBT37_yyzY",
			"instrumental": "No"
		},
		"P_717873": {
			"work_title": "Girls Chase Boys",
			"work_artist": "Trent Dabbs",
			"perf_title": "Girls Chase Boys",
			"perf_artist": "Piano Tribute Players",
			"release_year": "2014",
			"work_id": "W_190005",
			"perf_id": "P_717873",
			"yt_link": "http://www.youtube.com/embed/xFZtWgbTIsg",
			"instrumental": "Yes"
		}
	},
	"W_190008": {
		"P_717895": {
			"work_title": "Valar Morghulis",
			"work_artist": "Ramin Djawadi",
			"perf_title": "Valar Morghulis",
			"perf_artist": "Piano Tribute Players",
			"release_year": "2014",
			"work_id": "W_190008",
			"perf_id": "P_717895",
			"yt_link": "http://www.youtube.com/embed/dRN3DAqD48U",
			"instrumental": "Yes"
		}
	},
	"W_190009": {
		"P_717897": {
			"work_title": "What Is Dead May Never Die",
			"work_artist": "Ramin Djawadi",
			"perf_title": "What Is Dead May Never Die",
			"perf_artist": "Ramin Djawadi",
			"release_year": "2012",
			"work_id": "W_190009",
			"perf_id": "P_717897",
			"yt_link": "http://www.youtube.com/embed/Ha_o4yeai-k",
			"instrumental": "Yes"
		},
		"P_717898": {
			"work_title": "What Is Dead May Never Die",
			"work_artist": "Ramin Djawadi",
			"perf_title": "What Is Dead May Never Die",
			"perf_artist": "Piano Tribute Players",
			"release_year": "2014",
			"work_id": "W_190009",
			"perf_id": "P_717898",
			"yt_link": "http://www.youtube.com/embed/x4AMXU5QXMI",
			"instrumental": "Yes"
		}
	},
	"W_190010": {
		"P_717968": {
			"work_title": "It's Always Summer Under the Sea (Shireen's Song)",
			"work_artist": "Bryan Cogman",
			"perf_title": "It's Always Summer Under the Sea (Shireen's Song)",
			"perf_artist": "Kerry Ingram",
			"release_year": "2013",
			"work_id": "W_190010",
			"perf_id": "P_717968",
			"yt_link": "http://www.youtube.com/embed/YGLXZKIST2Q",
			"instrumental": "No"
		},
		"P_717970": {
			"work_title": "It's Always Summer Under the Sea (Shireen's Song)",
			"work_artist": "Bryan Cogman",
			"perf_title": "It's Always Summer Under the Sea",
			"perf_artist": "Piano Tribute Players",
			"release_year": "2014",
			"work_id": "W_190010",
			"perf_id": "P_717970",
			"yt_link": "http://www.youtube.com/embed/wl2xnzwyBEk",
			"instrumental": "Yes"
		}
	},
	"W_190016": {
		"P_717922": {
			"work_title": "Vain yhden kerran el\u00e4iss\u00e4\u00e4n",
			"work_artist": "Jori Sivonen",
			"perf_title": "Vain yhden kerran el\u00e4iss\u00e4\u00e4n",
			"perf_artist": "Tapani Kansa",
			"release_year": "1983",
			"work_id": "W_190016",
			"perf_id": "P_717922",
			"yt_link": "http://www.youtube.com/embed/hiaD1rZ0AUM",
			"instrumental": "No"
		}
	},
	"W_190025": {
		"P_717942": {
			"work_title": "Alter Ego",
			"work_artist": "Jean-Louis Aubert",
			"perf_title": "Alter Ego",
			"perf_artist": "Jean-Louis Aubert",
			"release_year": "2001",
			"work_id": "W_190025",
			"perf_id": "P_717942",
			"yt_link": "http://www.youtube.com/embed/6qpvDY6PYx4",
			"instrumental": "No"
		}
	},
	"W_190033": {
		"P_718000": {
			"work_title": "The Bear and the Maiden Fair",
			"work_artist": "Ramin Djawadi",
			"perf_title": "The Bear and the Maiden Fair",
			"perf_artist": "Piano Tribute Players",
			"release_year": "2014",
			"work_id": "W_190033",
			"perf_id": "P_718000",
			"yt_link": "http://www.youtube.com/embed/m0TdcqkcGdo",
			"instrumental": "Yes"
		}
	},
	"W_190034": {
		"P_718003": {
			"work_title": "For the Realm",
			"work_artist": "Ramin Djawadi",
			"perf_title": "For the Realm",
			"perf_artist": "Ramin Djawadi",
			"release_year": "2013",
			"work_id": "W_190034",
			"perf_id": "P_718003",
			"yt_link": "http://www.youtube.com/embed/nrkiogVgK-E",
			"instrumental": "Yes"
		},
		"P_718004": {
			"work_title": "For the Realm",
			"work_artist": "Ramin Djawadi",
			"perf_title": "For the Realm",
			"perf_artist": "Piano Tribute Players",
			"release_year": "2014",
			"work_id": "W_190034",
			"perf_id": "P_718004",
			"yt_link": "http://www.youtube.com/embed/hbi1tzA4-p0",
			"instrumental": "Yes"
		}
	},
	"W_190035": {
		"P_718016": {
			"work_title": "Memory Lane",
			"work_artist": "Gene Dozier",
			"perf_title": "Memory Lane",
			"perf_artist": "Lynne Fiddmont",
			"release_year": "2018",
			"work_id": "W_190035",
			"perf_id": "P_718016",
			"yt_link": "http://www.youtube.com/embed/_d1SOsGi68o",
			"instrumental": "No"
		}
	},
	"W_190037": {
		"P_718030": {
			"work_title": "King of the North",
			"work_artist": "Ramin Djawadi",
			"perf_title": "King of the North",
			"perf_artist": "Piano Tribute Players",
			"release_year": "2014",
			"work_id": "W_190037",
			"perf_id": "P_718030",
			"yt_link": "http://www.youtube.com/embed/aO-piHooBM8",
			"instrumental": "Yes"
		}
	},
	"W_189789": {
		"P_716992": {
			"work_title": "The Warmth",
			"work_artist": "Brandon Boyd",
			"perf_title": "The Warmth",
			"perf_artist": "Incubus",
			"release_year": "1999",
			"work_id": "W_189789",
			"perf_id": "P_716992",
			"yt_link": "http://www.youtube.com/embed/VeHddLI-aY8",
			"instrumental": "No"
		},
		"P_716993": {
			"work_title": "The Warmth",
			"work_artist": "Brandon Boyd",
			"perf_title": "The Warmth",
			"perf_artist": "The Section [Vitamin String Quartet]",
			"release_year": "2002",
			"work_id": "W_189789",
			"perf_id": "P_716993",
			"yt_link": "http://www.youtube.com/embed/VHpB40KtF9s",
			"instrumental": "Yes"
		}
	},
	"W_189790": {
		"P_716994": {
			"work_title": "Make Yourself",
			"work_artist": "Brandon Boyd",
			"perf_title": "Make Yourself",
			"perf_artist": "Incubus",
			"release_year": "1999",
			"work_id": "W_189790",
			"perf_id": "P_716994",
			"yt_link": "http://www.youtube.com/embed/sTfkd7dHVSM",
			"instrumental": "No"
		},
		"P_716995": {
			"work_title": "Make Yourself",
			"work_artist": "Brandon Boyd",
			"perf_title": "Make Yourself",
			"perf_artist": "The Section [Vitamin String Quartet]",
			"release_year": "2002",
			"work_id": "W_189790",
			"perf_id": "P_716995",
			"yt_link": "http://www.youtube.com/embed/OHlSCFnWYUM",
			"instrumental": "Yes"
		}
	},
	"W_189791": {
		"P_716996": {
			"work_title": "Mexico",
			"work_artist": "Brandon Boyd",
			"perf_title": "Mexico",
			"perf_artist": "Incubus",
			"release_year": "2001",
			"work_id": "W_189791",
			"perf_id": "P_716996",
			"yt_link": "http://www.youtube.com/embed/PNuCGqwYbVE",
			"instrumental": "No"
		},
		"P_716999": {
			"work_title": "Mexico",
			"work_artist": "Brandon Boyd",
			"perf_title": "Mexico",
			"perf_artist": "The Section [Vitamin String Quartet]",
			"release_year": "2002",
			"work_id": "W_189791",
			"perf_id": "P_716999",
			"yt_link": "http://www.youtube.com/embed/KeGAGe7-MF4",
			"instrumental": "Yes"
		}
	},
	"W_189792": {
		"P_717030": {
			"work_title": "Ritual",
			"work_artist": "Dan Reed",
			"perf_title": "Ritual",
			"perf_artist": "Dan Reed Network",
			"release_year": "1988",
			"work_id": "W_189792",
			"perf_id": "P_717030",
			"yt_link": "http://www.youtube.com/embed/g-Xav5OsTYo",
			"instrumental": "No"
		}
	},
	"W_189793": {
		"P_717000": {
			"work_title": "A Train That Never Runs",
			"work_artist": "Jerry Foster",
			"perf_title": "A Train That Never Runs",
			"perf_artist": "Bobby Bare",
			"release_year": "1973",
			"work_id": "W_189793",
			"perf_id": "P_717000",
			"yt_link": "http://www.youtube.com/embed/kWzhqr3oBzI",
			"instrumental": "No"
		}
	},
	"W_189796": {
		"P_717004": {
			"work_title": "The Aeroplane Flies High",
			"work_artist": "Billy Corgan",
			"perf_title": "The Aeroplane Flies High",
			"perf_artist": "The Smashing Pumpkins",
			"release_year": "1996",
			"work_id": "W_189796",
			"perf_id": "P_717004",
			"yt_link": "http://www.youtube.com/embed/_Zn5h_AT-NA",
			"instrumental": "No"
		},
		"P_717005": {
			"work_title": "The Aeroplane Flies High",
			"work_artist": "Billy Corgan",
			"perf_title": "Aeroplane Flies High",
			"perf_artist": "Vitamin String Quartet",
			"release_year": "2007",
			"work_id": "W_189796",
			"perf_id": "P_717005",
			"yt_link": "http://www.youtube.com/embed/6HmXAIibXoQ",
			"instrumental": "Yes"
		}
	},
	"W_189900": {
		"P_717408": {
			"work_title": "Begin the Begin",
			"work_artist": "Bill Berry",
			"perf_title": "Begin the Begin",
			"perf_artist": "R.E.M.",
			"release_year": "1986",
			"work_id": "W_189900",
			"perf_id": "P_717408",
			"yt_link": "http://www.youtube.com/embed/rePNg6MmdEQ",
			"instrumental": "No"
		}
	},
	"W_189902": {},
	"W_189904": {
		"P_717426": {
			"work_title": "Faust Arp",
			"work_artist": "Colin Greenwood",
			"perf_title": "Faust Arp",
			"perf_artist": "Vitamin String Quartet",
			"release_year": "2009",
			"work_id": "W_189904",
			"perf_id": "P_717426",
			"yt_link": "http://www.youtube.com/embed/fRT_iL1ZPk4",
			"instrumental": "Yes"
		}
	},
	"W_189911": {
		"P_717437": {
			"work_title": "Argentiinalainen tango",
			"work_artist": "Toivo K\u00e4rki",
			"perf_title": "Argentiinalainen tango",
			"perf_artist": "Eino Gr\u00f6n",
			"release_year": "1961",
			"work_id": "W_189911",
			"perf_id": "P_717437",
			"yt_link": "http://www.youtube.com/embed/aXov7p3vH8o",
			"instrumental": "No"
		}
	},
	"W_189918": {},
	"W_189928": {},
	"W_189930": {
		"P_717492": {
			"work_title": "Soulman",
			"work_artist": "Ben l'Oncle Soul",
			"perf_title": "Soulman",
			"perf_artist": "Ben L'Oncle Soul",
			"release_year": "2010",
			"work_id": "W_189930",
			"perf_id": "P_717492",
			"yt_link": "http://www.youtube.com/embed/69ptYXvUo7M",
			"instrumental": "No"
		},
		"P_717493": {
			"work_title": "Soulman",
			"work_artist": "Ben l'Oncle Soul",
			"perf_title": "Soulman",
			"perf_artist": "Rubby",
			"release_year": "2012",
			"work_id": "W_189930",
			"perf_id": "P_717493",
			"yt_link": "http://www.youtube.com/embed/3TB6ZCfLgUg",
			"instrumental": "No"
		}
	},
	"W_189931": {
		"P_717501": {
			"work_title": "Busted",
			"work_artist": "Rob Thomas",
			"perf_title": "Busted",
			"perf_artist": "Vitamin String Quartet",
			"release_year": "2002",
			"work_id": "W_189931",
			"perf_id": "P_717501",
			"yt_link": "http://www.youtube.com/embed/aPzk907cKC0",
			"instrumental": "Yes"
		}
	},
	"W_189932": {
		"P_717503": {
			"work_title": "Kody",
			"work_artist": "Rob Thomas",
			"perf_title": "Kody",
			"perf_artist": "Vitamin String Quartet",
			"release_year": "2002",
			"work_id": "W_189932",
			"perf_id": "P_717503",
			"yt_link": "http://www.youtube.com/embed/VpImTtRVB90",
			"instrumental": "Yes"
		}
	},
	"W_189933": {
		"P_717504": {
			"work_title": "Bed of Lies",
			"work_artist": "Matt Serletic",
			"perf_title": "Bed of Lies",
			"perf_artist": "Matchbox Twenty",
			"release_year": "2000",
			"work_id": "W_189933",
			"perf_id": "P_717504",
			"yt_link": "http://www.youtube.com/embed/gn_zRG4z9aQ",
			"instrumental": "No"
		},
		"P_717505": {
			"work_title": "Bed of Lies",
			"work_artist": "Matt Serletic",
			"perf_title": "Bed of Lies",
			"perf_artist": "Vitamin String Quartet",
			"release_year": "2002",
			"work_id": "W_189933",
			"perf_id": "P_717505",
			"yt_link": "http://www.youtube.com/embed/18hl9ZB4dQc",
			"instrumental": "Yes"
		}
	},
	"W_189934": {
		"P_717506": {
			"work_title": "Bent",
			"work_artist": "Rob Thomas",
			"perf_title": "Bent",
			"perf_artist": "Matchbox Twenty",
			"release_year": "2000",
			"work_id": "W_189934",
			"perf_id": "P_717506",
			"yt_link": "http://www.youtube.com/embed/969RAKkYESU",
			"instrumental": "No"
		},
		"P_717507": {
			"work_title": "Bent",
			"work_artist": "Rob Thomas",
			"perf_title": "Bent",
			"perf_artist": "Vitamin String Quartet",
			"release_year": "2002",
			"work_id": "W_189934",
			"perf_id": "P_717507",
			"yt_link": "http://www.youtube.com/embed/dwildjEvuew",
			"instrumental": "Yes"
		}
	},
	"W_189935": {
		"P_717508": {
			"work_title": "Leave",
			"work_artist": "Rob Thomas",
			"perf_title": "Leave",
			"perf_artist": "Matchbox Twenty",
			"release_year": "2000",
			"work_id": "W_189935",
			"perf_id": "P_717508",
			"yt_link": "http://www.youtube.com/embed/SB_m-C819yw",
			"instrumental": "No"
		},
		"P_717509": {
			"work_title": "Leave",
			"work_artist": "Rob Thomas",
			"perf_title": "Leave",
			"perf_artist": "Vitamin String Quartet",
			"release_year": "2002",
			"work_id": "W_189935",
			"perf_id": "P_717509",
			"yt_link": "http://www.youtube.com/embed/YmJydMSX5mM",
			"instrumental": "Yes"
		}
	},
	"W_189936": {
		"P_717510": {
			"work_title": "You Won't Be Mine",
			"work_artist": "Rob Thomas",
			"perf_title": "You Won't Be Mine",
			"perf_artist": "Matchbox Twenty",
			"release_year": "2000",
			"work_id": "W_189936",
			"perf_id": "P_717510",
			"yt_link": "http://www.youtube.com/embed/5WvXA6P2Po4",
			"instrumental": "No"
		}
	},
	"W_189937": {
		"P_717529": {
			"work_title": "American Dream",
			"work_artist": "Evan \"Kidd\" Bogart",
			"perf_title": "American Dream",
			"perf_artist": "MKTO",
			"release_year": "2014",
			"work_id": "W_189937",
			"perf_id": "P_717529",
			"yt_link": "http://www.youtube.com/embed/NPLeuBXoPXI",
			"instrumental": "No"
		},
		"P_717531": {
			"work_title": "American Dream",
			"work_artist": "Evan \"Kidd\" Bogart",
			"perf_title": "American Dream [MKTO]",
			"perf_artist": "Piano Tribute Players",
			"release_year": "2014",
			"work_id": "W_189937",
			"perf_id": "P_717531",
			"yt_link": "http://www.youtube.com/embed/4-4uvNTappE",
			"instrumental": "Yes"
		}
	},
	"W_189938": {
		"P_717535": {
			"work_title": "Could Be Me",
			"work_artist": "Evan \"Kidd\" Bogart",
			"perf_title": "Could Be Me",
			"perf_artist": "MKTO feat. Ne-Yo",
			"release_year": "2014",
			"work_id": "W_189938",
			"perf_id": "P_717535",
			"yt_link": "http://www.youtube.com/embed/CfwzWTWxLxc",
			"instrumental": "No"
		},
		"P_717537": {
			"work_title": "Could Be Me",
			"work_artist": "Evan \"Kidd\" Bogart",
			"perf_title": "Could Be Me",
			"perf_artist": "Piano Tribute Players",
			"release_year": "2014",
			"work_id": "W_189938",
			"perf_id": "P_717537",
			"yt_link": "http://www.youtube.com/embed/tlIj_1mFCI4",
			"instrumental": "Yes"
		}
	},
	"W_189941": {
		"P_717615": {
			"work_title": "Forever Until Tomorrow",
			"work_artist": "Evan \"Kidd\" Bogart",
			"perf_title": "Forever Until Tomorrow",
			"perf_artist": "MKTO",
			"release_year": "2014",
			"work_id": "W_189941",
			"perf_id": "P_717615",
			"yt_link": "http://www.youtube.com/embed/Hhbz6z7_Ahw",
			"instrumental": "No"
		},
		"P_717616": {
			"work_title": "Forever Until Tomorrow",
			"work_artist": "Evan \"Kidd\" Bogart",
			"perf_title": "Forever Until Tomorrow",
			"perf_artist": "Piano Tribute Players",
			"release_year": "2014",
			"work_id": "W_189941",
			"perf_id": "P_717616",
			"yt_link": "http://www.youtube.com/embed/NzYLHNRKzF0",
			"instrumental": "Yes"
		}
	},
	"W_189942": {
		"P_717617": {
			"work_title": "Goodbye Song",
			"work_artist": "Evan \"Kidd\" Bogart",
			"perf_title": "Goodbye Song",
			"perf_artist": "MKTO",
			"release_year": "2014",
			"work_id": "W_189942",
			"perf_id": "P_717617",
			"yt_link": "http://www.youtube.com/embed/uIAE2MgtJ28",
			"instrumental": "No"
		},
		"P_717618": {
			"work_title": "Goodbye Song",
			"work_artist": "Evan \"Kidd\" Bogart",
			"perf_title": "Goodbye Song",
			"perf_artist": "Piano Tribute Players",
			"release_year": "2014",
			"work_id": "W_189942",
			"perf_id": "P_717618",
			"yt_link": "http://www.youtube.com/embed/2IjBog_q1z4",
			"instrumental": "Yes"
		}
	},
	"W_189943": {
		"P_717619": {
			"work_title": "Heartbreak Holiday",
			"work_artist": "Evan \"Kidd\" Bogart",
			"perf_title": "Heartbreak Holiday",
			"perf_artist": "MKTO",
			"release_year": "2014",
			"work_id": "W_189943",
			"perf_id": "P_717619",
			"yt_link": "http://www.youtube.com/embed/I19PvW23mH8",
			"instrumental": "No"
		},
		"P_717620": {
			"work_title": "Heartbreak Holiday",
			"work_artist": "Evan \"Kidd\" Bogart",
			"perf_title": "Heartbreak Holiday",
			"perf_artist": "Piano Tribute Players",
			"release_year": "2014",
			"work_id": "W_189943",
			"perf_id": "P_717620",
			"yt_link": "http://www.youtube.com/embed/E5v4SjUpWeM",
			"instrumental": "Yes"
		}
	},
	"W_189944": {
		"P_717623": {
			"work_title": "No More Second Chances",
			"work_artist": "Evan \"Kidd\" Bogart",
			"perf_title": "No More Second Chances",
			"perf_artist": "MKTO feat. Jessica Ashley",
			"release_year": "2014",
			"work_id": "W_189944",
			"perf_id": "P_717623",
			"yt_link": "http://www.youtube.com/embed/tL99Gj1Ifok",
			"instrumental": "No"
		}
	},
	"W_189946": {
		"P_717625": {
			"work_title": "Nowhere",
			"work_artist": "Eric Bellinger",
			"perf_title": "Nowhere",
			"perf_artist": "MKTO",
			"release_year": "2014",
			"work_id": "W_189946",
			"perf_id": "P_717625",
			"yt_link": "http://www.youtube.com/embed/EHBBSfyF4Kw",
			"instrumental": "No"
		},
		"P_717626": {
			"work_title": "Nowhere",
			"work_artist": "Eric Bellinger",
			"perf_title": "Nowhere",
			"perf_artist": "Piano Tribute Players",
			"release_year": "2014",
			"work_id": "W_189946",
			"perf_id": "P_717626",
			"yt_link": "http://www.youtube.com/embed/e_rnufu1rSw",
			"instrumental": "Yes"
		}
	},
	"W_189947": {
		"P_717629": {
			"work_title": "Wasted",
			"work_artist": "Evan \"Kidd\" Bogart",
			"perf_title": "Wasted",
			"perf_artist": "MKTO",
			"release_year": "2014",
			"work_id": "W_189947",
			"perf_id": "P_717629",
			"yt_link": "http://www.youtube.com/embed/jG5oY7wotnM",
			"instrumental": "No"
		},
		"P_717631": {
			"work_title": "Wasted",
			"work_artist": "Evan \"Kidd\" Bogart",
			"perf_title": "Wasted",
			"perf_artist": "Piano Tribute Players",
			"release_year": "2014",
			"work_id": "W_189947",
			"perf_id": "P_717631",
			"yt_link": "http://www.youtube.com/embed/m4pxX3oHk4w",
			"instrumental": "Yes"
		}
	},
	"W_189948": {
		"P_717633": {
			"work_title": "Thank You",
			"work_artist": "Evan \"Kidd\" Bogart",
			"perf_title": "Thank You",
			"perf_artist": "MKTO",
			"release_year": "2012",
			"work_id": "W_189948",
			"perf_id": "P_717633",
			"yt_link": "http://www.youtube.com/embed/ayZKE1Wp1sE",
			"instrumental": "No"
		},
		"P_717634": {
			"work_title": "Thank You",
			"work_artist": "Evan \"Kidd\" Bogart",
			"perf_title": "Thank You",
			"perf_artist": "Piano Tribute Players",
			"release_year": "2014",
			"work_id": "W_189948",
			"perf_id": "P_717634",
			"yt_link": "http://www.youtube.com/embed/Yh2CStLPbf0",
			"instrumental": "Yes"
		}
	},
	"W_189949": {
		"P_717635": {
			"work_title": "God Only Knows",
			"work_artist": "Evan \"Kidd\" Bogart",
			"perf_title": "God Only Knows",
			"perf_artist": "MKTO",
			"release_year": "2013",
			"work_id": "W_189949",
			"perf_id": "P_717635",
			"yt_link": "http://www.youtube.com/embed/a0C5HfZa934",
			"instrumental": "No"
		},
		"P_717636": {
			"work_title": "God Only Knows",
			"work_artist": "Evan \"Kidd\" Bogart",
			"perf_title": "God Only Knows",
			"perf_artist": "Piano Tribute Players",
			"release_year": "2014",
			"work_id": "W_189949",
			"perf_id": "P_717636",
			"yt_link": "http://www.youtube.com/embed/i20gneZg63Q",
			"instrumental": "Yes"
		}
	},
	"W_189958": {
		"P_717663": {
			"work_title": "No Stress",
			"work_artist": "Laurent Wolf",
			"perf_title": "No Stress",
			"perf_artist": "Laurent Wolf feat. Eric Carter",
			"release_year": "2008",
			"work_id": "W_189958",
			"perf_id": "P_717663",
			"yt_link": "http://www.youtube.com/embed/bVRnMrl2oj8",
			"instrumental": "No"
		},
		"P_717664": {
			"work_title": "No Stress",
			"work_artist": "Laurent Wolf",
			"perf_title": "No Stress",
			"perf_artist": "Lise Darly",
			"release_year": "2012",
			"work_id": "W_189958",
			"perf_id": "P_717664",
			"yt_link": "http://www.youtube.com/embed/TxxmjaX-5gE",
			"instrumental": "No"
		}
	},
	"W_189959": {
		"P_717665": {
			"work_title": "Immortelle",
			"work_artist": "Rick Allison",
			"perf_title": "Immortelle",
			"perf_artist": "Lara Fabian",
			"release_year": "2001",
			"work_id": "W_189959",
			"perf_id": "P_717665",
			"yt_link": "http://www.youtube.com/embed/99_BOsxIt6w",
			"instrumental": "No"
		},
		"P_717666": {
			"work_title": "Immortelle",
			"work_artist": "Rick Allison",
			"perf_title": "Immortelle",
			"perf_artist": "Dominique Magloire",
			"release_year": "2012",
			"work_id": "W_189959",
			"perf_id": "P_717666",
			"yt_link": "http://www.youtube.com/embed/jY4_aAQbe04",
			"instrumental": "No"
		}
	},
	"W_189960": {
		"P_717668": {
			"work_title": "Divine idylle",
			"work_artist": "-M- [Matthieu Ch\u00e9did]",
			"perf_title": "Divine idylle",
			"perf_artist": "Vanessa Paradis",
			"release_year": "2007",
			"work_id": "W_189960",
			"perf_id": "P_717668",
			"yt_link": "http://www.youtube.com/embed/3R_6sP_6VWE",
			"instrumental": "No"
		},
		"P_717669": {
			"work_title": "Divine idylle",
			"work_artist": "-M- [Matthieu Ch\u00e9did]",
			"perf_title": "Divine idylle",
			"perf_artist": "Sacha [Tran]",
			"release_year": "2012",
			"work_id": "W_189960",
			"perf_id": "P_717669",
			"yt_link": "http://www.youtube.com/embed/EqQmtzhX4OQ",
			"instrumental": "No"
		}
	},
	"W_189970": {
		"P_717695": {
			"work_title": "Final Masquerade",
			"work_artist": "Chester Bennington",
			"perf_title": "Final Masquerade",
			"perf_artist": "Linkin Park",
			"release_year": "2014",
			"work_id": "W_189970",
			"perf_id": "P_717695",
			"yt_link": "http://www.youtube.com/embed/i8q8fFs3kTM",
			"instrumental": "No"
		},
		"P_717697": {
			"work_title": "Final Masquerade",
			"work_artist": "Chester Bennington",
			"perf_title": "Final Masquerade",
			"perf_artist": "Piano Tribute Players",
			"release_year": "2014",
			"work_id": "W_189970",
			"perf_id": "P_717697",
			"yt_link": "http://www.youtube.com/embed/s64C_gTZKx4",
			"instrumental": "Yes"
		}
	},
	"W_189974": {
		"P_717710": {
			"work_title": "Come with Me Now",
			"work_artist": "Johnny Kongos",
			"perf_title": "Come with Me Now",
			"perf_artist": "KONGOS",
			"release_year": "2012",
			"work_id": "W_189974",
			"perf_id": "P_717710",
			"yt_link": "http://www.youtube.com/embed/Hq_J-XVOucg",
			"instrumental": "No"
		}
	},
	"W_189982": {}
}